Workbook

Sheet README
A1: Securitisation Risk Analytics - Excel Validation Workbook
A3: Purpose: independent cross-check of (1) IFRS 9 ECL and (2) the 36-month tranche waterfall used in the Power BI model.
A4: Colour code: BLUE = hard-coded input or value pasted from the Python / CSV outputs; BLACK = formula. Yellow cell = the one you change.
A6: Sheets
A7: Assumptions - calibrated parameters (from dynamic_loss_monthly and the tape), scenario table, tranche structure. Change the scenario in B10.
A8: Waterfall - month-by-month waterfall rebuilt in Excel formulas; compares to the Python engine and checks cash conservation.
A9: Python_Results - end balances produced by securitisation_pipeline.py for all six scenarios (comparison source).
A10: ECL_LoanLevel - loan-level recomputation: tape ECL vs PD x LGD x EAD, and the challenger ECL from the transition-matrix PD term structure.
A11: PD_TermStructure - cumulative PD by starting DPD bucket and horizon (from the empirical roll-rate matrix).
A12: ECL_Summary - stage-level reconciliation and PASS/FAIL checks.
A14: Key assumptions (also listed in Assumptions): tranche sizes/coupons, 0.5% servicing fee and trigger levels are ASSUMED - the brief gives none.
A15: Challenger LGD = net loss severity from dynamic_loss_monthly (NetLoss / NewDefaults_Balance).
... A17: Data issues found in the supplied files are in powerbi_data/DataQualityLog.csv - read them before relying on any figure.

Sheet Assumptions
A1: Assumptions and scenario selector
A3: Pool net LGD (severity) | B3: 0.41471957 | C3: dynamic_loss_monthly: NetLoss / NewDefaults_Balance
A4: Base annual CDR | B4: 0.035767773 | C4: dynamic_loss_monthly: NewDefaults_Balance / BOP_Balance, annualised
A5: Base annual CPR | B5: 0.092378661 | C5: dynamic_loss_monthly: Prepayments / BOP_Balance, annualised
A6: Pool WAC | B6: 0.10945451 | C6: tape: InterestRate weighted by CurrentBalance
A7: Pool WAM (months) | B7: 45.142781 | C7: tape: RemainingTerm weighted by CurrentBalance
A8: Pool balance | B8: 3.177852e+08 | C8: tape: sum CurrentBalance
A9: Servicing fee (p.a.) | B9: 0.005 | C9: ASSUMPTION
A10: SELECTED SCENARIO ID (1-6) | B10: 4 | C10: Change this cell; the Waterfall sheet and its Python comparison update. 1=Base ... 6=Rate Shock
A11: Selected annual CDR | B11: =INDEX($F$18:$F$23,MATCH($B$10,$A$18:$A$23,0)) -> 0.12519
A12: Selected annual CPR | B12: =INDEX($G$18:$G$23,MATCH($B$10,$A$18:$A$23,0)) -> 0.05238
A13: Selected pool LGD | B13: =INDEX($H$18:$H$23,MATCH($B$10,$A$18:$A$23,0)) -> 0.5647
A14: Monthly default rate (MDR) | B14: =1-(1-B11)^(1/12) -> 0.01108383
A15: Single monthly mortality (SMM) | B15: =1-(1-B12)^(1/12) -> 0.0044734393
A17: ID | B17: Scenario | C17: Weight | D17: CDR multiple | E17: CPR change | F17: Annual CDR | G17: Annual CPR | H17: Pool LGD | I17: PD multiplier | J17: LGD add
A18: 1 | B18: Base | C18: 0.5 | D18: 1 | E18: 0 | F18: =ROUND(MIN(0.6,$B$4*D18),5) -> 0.03577 | G18: =ROUND(MAX(0.01,$B$5+E18),5) -> 0.09238 | H18: =ROUND(MIN(0.95,MAX(0.1,$B$3+J18)),4) -> 0.4147 | I18: 1 | J18: 0
A19: 2 | B19: Upside | C19: 0.1 | D19: 0.6 | E19: 0.02 | F19: =ROUND(MIN(0.6,$B$4*D19),5) -> 0.02146 | G19: =ROUND(MAX(0.01,$B$5+E19),5) -> 0.11238 | H19: =ROUND(MIN(0.95,MAX(0.1,$B$3+J19)),4) -> 0.3847 | I19: 0.8 | J19: -0.03
A20: 3 | B20: Moderate Stress | C20: 0.25 | D20: 2 | E20: -0.02 | F20: =ROUND(MIN(0.6,$B$4*D20),5) -> 0.07154 | G20: =ROUND(MAX(0.01,$B$5+E20),5) -> 0.07238 | H20: =ROUND(MIN(0.95,MAX(0.1,$B$3+J20)),4) -> 0.4847 | I20: 1.5 | J20: 0.07
A21: 4 | B21: Severe Stress | C21: 0.15 | D21: 3.5 | E21: -0.04 | F21: =ROUND(MIN(0.6,$B$4*D21),5) -> 0.12519 | G21: =ROUND(MAX(0.01,$B$5+E21),5) -> 0.05238 | H21: =ROUND(MIN(0.95,MAX(0.1,$B$3+J21)),4) -> 0.5647 | I21: 2.5 | J21: 0.15
A22: 5 | B22: Crisis (GFC-style) | C22: 0 | D22: 6 | E22: -0.06 | F22: =ROUND(MIN(0.6,$B$4*D22),5) -> 0.21461 | G22: =ROUND(MAX(0.01,$B$5+E22),5) -> 0.03238 | H22: =ROUND(MIN(0.95,MAX(0.1,$B$3+J22)),4) -> 0.6647 | I22: 4 | J22: 0.25
A23: 6 | B23: Rate Shock | C23: 0 | D23: 2 | E23: -0.03 | F23: =ROUND(MIN(0.6,$B$4*D23),5) -> 0.07154 | G23: =ROUND(MAX(0.01,$B$5+E23),5) -> 0.06238 | H23: =ROUND(MIN(0.95,MAX(0.1,$B$3+J23)),4) -> 0.4447 | I23: 1.6 | J23: 0.03
A26: Tranche | B26: Size % of pool | C26: Coupon | D26: Attachment | E26: Detachment | F26: Note
A27: Class A (Senior) | B27: 0.8 | C27: 0.07 | D27: 0.2 | E27: 1 | F27: ASSUMED structure - brief supplies no tranche terms
A28: Class B (Mezzanine) | B28: 0.12 | C28: 0.085 | D28: 0.08 | E28: 0.2 | F28: ASSUMED structure - brief supplies no tranche terms
A29: Class C (Junior) | B29: 0.05 | C29: 0.115 | D29: 0.03 | E29: 0.08 | F29: ASSUMED structure - brief supplies no tranche terms
A30: Equity / Residual | B30: 0.03 | C30: 0 | D30: 0 | E30: 0.03 | F30: ASSUMED structure - brief supplies no tranche terms
A31: Check: sizes sum to 100% | B31: =SUM(B27:B30) -> 1

Sheet ECL_Summary
A1: ECL reconciliation by IFRS 9 stage
A3: Stage | B3: Loans | C3: EAD | D3: ECL (tape) | E3: ECL recomputed | F3: Variance | G3: Coverage % (tape) | H3: Challenger ECL | I3: Coverage % (challenger) | J3: Challenger vs tape
A4: 1 | B4: =COUNTIF(ECL_LoanLevel!$B$6:$B$505,A4) -> 422 | C4: =SUMIFS(ECL_LoanLevel!$H$6:$H$505,ECL_LoanLevel!$B$6:$B$505,A4) -> 2.8008928e+08 | D4: =SUMIFS(ECL_LoanLevel!$I$6:$I$505,ECL_LoanLevel!$B$6:$B$505,A4) -> 2792098.3 | E4: =SUMIFS(ECL_LoanLevel!$J$6:$J$505,ECL_LoanLevel!$B$6:$B$505,A4) -> 2792098.2 | F4: =E4-D4 -> -0.0289918 | G4: =IF(C4=0,0,D4/C4) -> 0.0099686011 | H4: =SUMIFS(ECL_LoanLevel!$O$6:$O$505,ECL_LoanLevel!$B$6:$B$505,A4) -> 12568133 | I4: =IF(C4=0,0,H4/C4) -> 0.044871883 | J4: =IF(D4=0,0,H4/D4-1) -> 3.501322
A5: 2 | B5: =COUNTIF(ECL_LoanLevel!$B$6:$B$505,A5) -> 45 | C5: =SUMIFS(ECL_LoanLevel!$H$6:$H$505,ECL_LoanLevel!$B$6:$B$505,A5) -> 27890557 | D5: =SUMIFS(ECL_LoanLevel!$I$6:$I$505,ECL_LoanLevel!$B$6:$B$505,A5) -> 1648395 | E5: =SUMIFS(ECL_LoanLevel!$J$6:$J$505,ECL_LoanLevel!$B$6:$B$505,A5) -> 1648395 | F5: =E5-D5 -> 0.00034829532 | G5: =IF(C5=0,0,D5/C5) -> 0.059102264 | H5: =SUMIFS(ECL_LoanLevel!$O$6:$O$505,ECL_LoanLevel!$B$6:$B$505,A5) -> 9529024.1 | I5: =IF(C5=0,0,H5/C5) -> 0.34165772 | J5: =IF(D5=0,0,H5/D5-1) -> 4.7807891
A6: 3 | B6: =COUNTIF(ECL_LoanLevel!$B$6:$B$505,A6) -> 33 | C6: =SUMIFS(ECL_LoanLevel!$H$6:$H$505,ECL_LoanLevel!$B$6:$B$505,A6) -> 18184337 | D6: =SUMIFS(ECL_LoanLevel!$I$6:$I$505,ECL_LoanLevel!$B$6:$B$505,A6) -> 7222459.6 | E6: =SUMIFS(ECL_LoanLevel!$J$6:$J$505,ECL_LoanLevel!$B$6:$B$505,A6) -> 7222459.6 | F6: =E6-D6 -> -0.016415273 | G6: =IF(C6=0,0,D6/C6) -> 0.39718025 | H6: =SUMIFS(ECL_LoanLevel!$O$6:$O$505,ECL_LoanLevel!$B$6:$B$505,A6) -> 7358263.5 | I6: =IF(C6=0,0,H6/C6) -> 0.40464842 | J6: =IF(D6=0,0,H6/D6-1) -> 0.018802994
A7: Total | B7: =SUM(B4:B6) -> 500 | C7: =SUM(C4:C6) -> 3.2616417e+08 | D7: =SUM(D4:D6) -> 11662953 | E7: =SUM(E4:E6) -> 11662953 | F7: =SUM(F4:F6) -> -0.045058778 | G7: =IF(C7=0,0,D7/C7) -> 0.035757922 | H7: =SUM(H4:H6) -> 29455421 | I7: =IF(C7=0,0,H7/C7) -> 0.090308573 | J7: =IF(D7=0,0,H7/D7-1) -> 1.5255543
A9: Checks
A10: Tape ECL = PD x LGD x EAD (max loan-level variance < 0.05) | E10: =MAX(MAX(ECL_LoanLevel!$K$6:$K$505),-MIN(ECL_LoanLevel!$K$6:$K$505)) -> 0.0049868904 | F10: =IF(E10<0.05,"PASS","FAIL") -> PASS
A11: Excel challenger ECL = Python challenger ECL (max loan diff < 0.05) | E11: =MAX(MAX(ECL_LoanLevel!$Q$6:$Q$505),-MIN(ECL_LoanLevel!$Q$6:$Q$505)) -> 0.0049950144 | F11: =IF(E11<0.05,"PASS","FAIL") -> PASS
A12: Stage ECL sums to total tape ECL | E12: =SUM(ECL_LoanLevel!$I$6:$I$505)-D7 -> 0 | F12: =IF(ABS(E12)<0.5,"PASS","FAIL") -> PASS
A14: Reading the result
A15: The tape ECL is internally consistent (PD x LGD x EAD), but the challenger is materially higher.
A16: Reason: the tape PD for Stage 1 is about 2%, while the roll-rate matrix in dpd_snapshot_history implies a 12-month PD of about 11% for loans starting 'Current'.
A17: Caveats: only 11 monthly transitions, 31 observed entries into 90+, Markov and time-homogeneity assumptions, and the duplicated-May snapshot (see DataQualityLog DQ05).
A18: Treat the gap as a model-risk finding to discuss in the report, not as a corrected provision.

Sheet Python_Results
A1: scenario_id | B1: period | C1: ending_pool | D1: Class A end | E1: Class B end | F1: Class C end | G1: Equity end
A2: 1 | B2: 1 | C2: 3.0731147e+08 | D2: 2.4375443e+08 | E2: 38134224 | F2: 15889260 | G2: 9533556.1
A3: 1 | B3: 2 | C3: 2.9703043e+08 | D3: 2.3347339e+08 | E3: 38134224 | F3: 15889260 | G3: 9533556.1
A4: 1 | B4: 3 | C4: 2.869391e+08 | D4: 2.2338206e+08 | E4: 38134224 | F4: 15889260 | G4: 9533556.1
A5: 1 | B5: 4 | C5: 2.7703453e+08 | D5: 2.1347749e+08 | E5: 38134224 | F5: 15889260 | G5: 9533556.1
A6: 1 | B6: 5 | C6: 2.6731384e+08 | D6: 2.037568e+08 | E6: 38134224 | F6: 15889260 | G6: 9533556.1
A7: 1 | B7: 6 | C7: 2.5777416e+08 | D7: 1.9421712e+08 | E7: 38134224 | F7: 15889260 | G7: 9533556.1
A8: 1 | B8: 7 | C8: 2.484127e+08 | D8: 1.8485566e+08 | E8: 38134224 | F8: 15889260 | G8: 9533556.1
A9: 1 | B9: 8 | C9: 2.3922666e+08 | D9: 1.7566962e+08 | E9: 38134224 | F9: 15889260 | G9: 9533556.1
A10: 1 | B10: 9 | C10: 2.3021332e+08 | D10: 1.6665628e+08 | E10: 38134224 | F10: 15889260 | G10: 9533556.1
A11: 1 | B11: 10 | C11: 2.2136998e+08 | D11: 1.5781294e+08 | E11: 38134224 | F11: 15889260 | G11: 9533556.1
A12: 1 | B12: 11 | C12: 2.1269399e+08 | D12: 1.4913695e+08 | E12: 38134224 | F12: 15889260 | G12: 9533556.1
A13: 1 | B13: 12 | C13: 2.0418273e+08 | D13: 1.4062569e+08 | E13: 38134224 | F13: 15889260 | G13: 9533556.1
... A217: 6 | B217: 36 | C217: 42461357 | D217: 0 | E217: 18566595 | F217: 15889260 | G217: 8005502.3

Sheet Waterfall
A1: Waterfall validation - Excel rebuild vs Python engine
A2: Selected scenario: | B2: =INDEX(Assumptions!$B$18:$B$23,MATCH(Assumptions!$B$10,Assumptions!$A$18:$A$23,0)) -> Severe Stress | D2: Max abs difference vs Python (any column): | H2: =MAX(MAX(AW7:BA42),-MIN(AW7:BA42)) -> 0.0049493285 | I2: =IF(H2<1,"PASS","FAIL") -> PASS
D3: Max abs cash-conservation gap (notes - pool): | H3: =MAX(MAX(AQ7:AQ42),-MIN(AQ7:AQ42)) -> 0 | I3: =IF(H3<1,"PASS","FAIL") -> PASS
A6: Period | B6: Beg pool | C6: Defaults | D6: Performing | E6: Prepay | F6: Sched principal | G6: Interest coll | H6: Recoveries | I6: Net loss | J6: Servicing fee | K6: Avail interest | L6: Beg A | M6: Beg B | N6: Beg C | O6: Beg Equity | P6: Coupon due A | Q6: Coupon due B | R6: Coupon due C | S6: Paid A | T6: Paid B | U6: Paid C | V6: Excess spread | W6: Cover for losses | X6: Residual to equity | Y6: WD Equity | Z6: WD C | AA6: WD B | AB6: WD A | AC6: A after WD | AD6: C after WD | AE6: B after WD | AF6: Eq after WD | AG6: Principal avail | AH6: Prin A | AI6: Prin B | AJ6: Prin C | AK6: Prin Eq | AL6: End A | AM6: End B | AN6: End C | AO6: End Equity | AP6: End pool | AQ6: Notes - pool | AR6: Python end pool | AS6: Python A | AT6: Python B | AU6: Python C | AV6: Python Eq | AW6: Diff pool | AX6: Diff A | AY6: Diff B | AZ6: Diff C | BA6: Diff Eq
A7: 1 | B7: =Assumptions!$B$8 -> 3.177852e+08 | C7: =B7*Assumptions!$B$14 -> 3522277.1 | D7: =B7-C7 -> 3.1426293e+08 | E7: =D7*Assumptions!$B$15 -> 1405836.1 | F7: =(D7-E7)/MAX(Assumptions!$B$7-A7+1,1) -> 6930390.2 | G7: =D7*Assumptions!$B$6/12 -> 2866457.8 | H7: =C7*(1-Assumptions!$B$13) -> 1533247.2 | I7: =C7*Assumptions!$B$13 -> 1989029.9 | J7: =B7*Assumptions!$B$9/12 -> 132410.5 | K7: =MAX(G7-J7,0) -> 2734047.3 | L7: =Assumptions!$B$8*Assumptions!$B$27 -> 2.5422816e+08 | M7: =Assumptions!$B$8*Assumptions!$B$28 -> 38134224 | N7: =Assumptions!$B$8*Assumptions!$B$29 -> 15889260 | O7: =Assumptions!$B$8*Assumptions!$B$30 -> 9533556.1 | P7: =L7*Assumptions!$C$27/12 -> 1482997.6 | Q7: =M7*Assumptions!$C$28/12 -> 270117.42 | R7: =N7*Assumptions!$C$29/12 -> 152272.08 | S7: =MIN(P7,K7) -> 1482997.6 | T7: =MIN(Q7,K7-S7) -> 270117.42 | U7: =MIN(R7,K7-S7-T7) -> 152272.08 | V7: =K7-S7-T7-U7 -> 828660.23 | W7: =MIN(V7,I7) -> 828660.23 | X7: =V7-W7 -> 0 | Y7: =MIN(O7,I7-W7) -> 1160369.7 | Z7: =MIN(N7,I7-W7-Y7) -> 0 | AA7: =MIN(M7,I7-W7-Y7-Z7) -> 0 | AB7: =MIN(L7,I7-W7-Y7-Z7-AA7) -> 0 | AC7: =L7-AB7 -> 2.5422816e+08 | AD7: =N7-Z7 -> 15889260 | AE7: =M7-AA7 -> 38134224 | AF7: =O7-Y7 -> 8373186.4 | AG7: =F7+E7+H7+W7 -> 10698134 | AH7: =MIN(AC7,AG7) -> 10698134 | AI7: =MIN(AE7,AG7-AH7) -> 0 | AJ7: =MIN(AD7,AG7-AH7-AI7) -> 0 | AK7: =MIN(AF7,AG7-AH7-AI7-AJ7) -> 0 | AL7: =AC7-AH7 -> 2.4353003e+08 | AM7: =AE7-AI7 -> 38134224 | AN7: =AD7-AJ7 -> 15889260 | AO7: =AF7-AK7 -> 8373186.4 | AP7: =D7-E7-F7 -> 3.059267e+08 | AQ7: =SUM(AL7:AO7)-AP7 -> 0 | AR7: =SUMIFS(Python_Results!$C$2:$C$217,Python_Results!$A$2:$A$217,Assumptions!$B$10,Python_Results!$B$2:$B$217,A7) -> 3.059267e+08 | AS7: =SUMIFS(Python_Results!$D$2:$D$217,Python_Results!$A$2:$A$217,Assumptions!$B$10,Python_Results!$B$2:$B$217,A7) -> 2.4353003e+08 | AT7: =SUMIFS(Python_Results!$E$2:$E$217,Python_Results!$A$2:$A$217,Assumptions!$B$10,Python_Results!$B$2:$B$217,A7) -> 38134224 | AU7: =SUMIFS(Python_Results!$F$2:$F$217,Python_Results!$A$2:$A$217,Assumptions!$B$10,Python_Results!$B$2:$B$217,A7) -> 15889260 | AV7: =SUMIFS(Python_Results!$G$2:$G$217,Python_Results!$A$2:$A$217,Assumptions!$B$10,Python_Results!$B$2:$B$217,A7) -> 8373186.4 | AW7: =AP7-AR7 -> 0.00060749054 | AX7: =AL7-AS7 -> -0.0038158298 | AY7: =AM7-AT7 -> -0.003200002 | AZ7: =AN7-AU7 -> -0.0029999986 | BA7: =AO7-AV7 -> 0.00062332675
A8: 2 | B8: =AP7 -> 3.059267e+08 | C8: =B8*Assumptions!$B$14 -> 3390839.5 | D8: =B8-C8 -> 3.0253586e+08 | E8: =D8*Assumptions!$B$15 -> 1353375.8 | F8: =(D8-E8)/MAX(Assumptions!$B$7-A8+1,1) -> 6822915.9 | G8: =D8*Assumptions!$B$6/12 -> 2759492.8 | H8: =C8*(1-Assumptions!$B$13) -> 1476032.4 | I8: =C8*Assumptions!$B$13 -> 1914807.1 | J8: =B8*Assumptions!$B$9/12 -> 127469.46 | K8: =MAX(G8-J8,0) -> 2632023.4 | L8: =AL7 -> 2.4353003e+08 | M8: =AM7 -> 38134224 | N8: =AN7 -> 15889260 | O8: =AO7 -> 8373186.4 | P8: =L8*Assumptions!$C$27/12 -> 1420591.8 | Q8: =M8*Assumptions!$C$28/12 -> 270117.42 | R8: =N8*Assumptions!$C$29/12 -> 152272.08 | S8: =MIN(P8,K8) -> 1420591.8 | T8: =MIN(Q8,K8-S8) -> 270117.42 | U8: =MIN(R8,K8-S8-T8) -> 152272.08 | V8: =K8-S8-T8-U8 -> 789042.04 | W8: =MIN(V8,I8) -> 789042.04 | X8: =V8-W8 -> 0 | Y8: =MIN(O8,I8-W8) -> 1125765 | Z8: =MIN(N8,I8-W8-Y8) -> 0 | AA8: =MIN(M8,I8-W8-Y8-Z8) -> 0 | AB8: =MIN(L8,I8-W8-Y8-Z8-AA8) -> 0 | AC8: =L8-AB8 -> 2.4353003e+08 | AD8: =N8-Z8 -> 15889260 | AE8: =M8-AA8 -> 38134224 | AF8: =O8-Y8 -> 7247421.4 | AG8: =F8+E8+H8+W8 -> 10441366 | AH8: =MIN(AC8,AG8) -> 10441366 | AI8: =MIN(AE8,AG8-AH8) -> 0 | AJ8: =MIN(AD8,AG8-AH8-AI8) -> 0 | AK8: =MIN(AF8,AG8-AH8-AI8-AJ8) -> 0 | AL8: =AC8-AH8 -> 2.3308866e+08 | AM8: =AE8-AI8 -> 38134224 | AN8: =AD8-AJ8 -> 15889260 | AO8: =AF8-AK8 -> 7247421.4 | AP8: =D8-E8-F8 -> 2.9435957e+08 | AQ8: =SUM(AL8:AO8)-AP8 -> 0 | AR8: =SUMIFS(Python_Results!$C$2:$C$217,Python_Results!$A$2:$A$217,Assumptions!$B$10,Python_Results!$B$2:$B$217,A8) -> 2.9435957e+08 | AS8: =SUMIFS(Python_Results!$D$2:$D$217,Python_Results!$A$2:$A$217,Assumptions!$B$10,Python_Results!$B$2:$B$217,A8) -> 2.3308866e+08 | AT8: =SUMIFS(Python_Results!$E$2:$E$217,Python_Results!$A$2:$A$217,Assumptions!$B$10,Python_Results!$B$2:$B$217,A8) -> 38134224 | AU8: =SUMIFS(Python_Results!$F$2:$F$217,Python_Results!$A$2:$A$217,Assumptions!$B$10,Python_Results!$B$2:$B$217,A8) -> 15889260 | AV8: =SUMIFS(Python_Results!$G$2:$G$217,Python_Results!$A$2:$A$217,Assumptions!$B$10,Python_Results!$B$2:$B$217,A8) -> 7247421.4 | AW8: =AP8-AR8 -> 0.001437068 | AX8: =AL8-AS8 -> 0.003439337 | AY8: =AM8-AT8 -> -0.003200002 | AZ8: =AN8-AU8 -> -0.0029999986 | BA8: =AO8-AV8 -> 0.0041977903
A9: 3 | B9: =AP8 -> 2.9435957e+08 | C9: =B9*Assumptions!$B$14 -> 3262631.4 | D9: =B9-C9 -> 2.9109694e+08 | E9: =D9*Assumptions!$B$15 -> 1302204.5 | F9: =(D9-E9)/MAX(Assumptions!$B$7-A9+1,1) -> 6717108.2 | G9: =D9*Assumptions!$B$6/12 -> 2655156 | H9: =C9*(1-Assumptions!$B$13) -> 1420223.4 | I9: =C9*Assumptions!$B$13 -> 1842407.9 | J9: =B9*Assumptions!$B$9/12 -> 122649.82 | K9: =MAX(G9-J9,0) -> 2532506.2 | L9: =AL8 -> 2.3308866e+08 | M9: =AM8 -> 38134224 | N9: =AN8 -> 15889260 | O9: =AO8 -> 7247421.4 | P9: =L9*Assumptions!$C$27/12 -> 1359683.9 | Q9: =M9*Assumptions!$C$28/12 -> 270117.42 | R9: =N9*Assumptions!$C$29/12 -> 152272.08 | S9: =MIN(P9,K9) -> 1359683.9 | T9: =MIN(Q9,K9-S9) -> 270117.42 | U9: =MIN(R9,K9-S9-T9) -> 152272.08 | V9: =K9-S9-T9-U9 -> 750432.84 | W9: =MIN(V9,I9) -> 750432.84 | X9: =V9-W9 -> 0 | Y9: =MIN(O9,I9-W9) -> 1091975.1 | Z9: =MIN(N9,I9-W9-Y9) -> 0 | AA9: =MIN(M9,I9-W9-Y9-Z9) -> 0 | AB9: =MIN(L9,I9-W9-Y9-Z9-AA9) -> 0 | AC9: =L9-AB9 -> 2.3308866e+08 | AD9: =N9-Z9 -> 15889260 | AE9: =M9-AA9 -> 38134224 | AF9: =O9-Y9 -> 6155446.3 | AG9: =F9+E9+H9+W9 -> 10189969 | AH9: =MIN(AC9,AG9) -> 10189969 | AI9: =MIN(AE9,AG9-AH9) -> 0 | AJ9: =MIN(AD9,AG9-AH9-AI9) -> 0 | AK9: =MIN(AF9,AG9-AH9-AI9-AJ9) -> 0 | AL9: =AC9-AH9 -> 2.2289869e+08 | AM9: =AE9-AI9 -> 38134224 | AN9: =AD9-AJ9 -> 15889260 | AO9: =AF9-AK9 -> 6155446.3 | AP9: =D9-E9-F9 -> 2.8307762e+08 | AQ9: =SUM(AL9:AO9)-AP9 -> 0 | AR9: =SUMIFS(Python_Results!$C$2:$C$217,Python_Results!$A$2:$A$217,Assumptions!$B$10,Python_Results!$B$2:$B$217,A9) -> 2.8307762e+08 | AS9: =SUMIFS(Python_Results!$D$2:$D$217,Python_Results!$A$2:$A$217,Assumptions!$B$10,Python_Results!$B$2:$B$217,A9) -> 2.2289869e+08 | AT9: =SUMIFS(Python_Results!$E$2:$E$217,Python_Results!$A$2:$A$217,Assumptions!$B$10,Python_Results!$B$2:$B$217,A9) -> 38134224 | AU9: =SUMIFS(Python_Results!$F$2:$F$217,Python_Results!$A$2:$A$217,Assumptions!$B$10,Python_Results!$B$2:$B$217,A9) -> 15889260 | AV9: =SUMIFS(Python_Results!$G$2:$G$217,Python_Results!$A$2:$A$217,Assumptions!$B$10,Python_Results!$B$2:$B$217,A9) -> 6155446.3 | AW9: =AP9-AR9 -> 0.0046865344 | AX9: =AL9-AS9 -> 0.002340436 | AY9: =AM9-AT9 -> -0.003200002 | AZ9: =AN9-AU9 -> -0.0029999986 | BA9: =AO9-AV9 -> -0.0014538271
A10: 4 | B10: =AP9 -> 2.8307762e+08 | C10: =B10*Assumptions!$B$14 -> 3137584.2 | D10: =B10-C10 -> 2.7994004e+08 | E10: =D10*Assumptions!$B$15 -> 1252294.8 | F10: =(D10-E10)/MAX(Assumptions!$B$7-A10+1,1) -> 6612941.4 | G10: =D10*Assumptions!$B$6/12 -> 2553391.6 | H10: =C10*(1-Assumptions!$B$13) -> 1365790.4 | I10: =C10*Assumptions!$B$13 -> 1771793.8 | J10: =B10*Assumptions!$B$9/12 -> 117949.01 | K10: =MAX(G10-J10,0) -> 2435442.6 | L10: =AL9 -> 2.2289869e+08 | M10: =AM9 -> 38134224 | N10: =AN9 -> 15889260 | O10: =AO9 -> 6155446.3 | P10: =L10*Assumptions!$C$27/12 -> 1300242.4 | Q10: =M10*Assumptions!$C$28/12 -> 270117.42 | R10: =N10*Assumptions!$C$29/12 -> 152272.08 | S10: =MIN(P10,K10) -> 1300242.4 | T10: =MIN(Q10,K10-S10) -> 270117.42 | U10: =MIN(R10,K10-S10-T10) -> 152272.08 | V10: =K10-S10-T10-U10 -> 712810.74 | W10: =MIN(V10,I10) -> 712810.74 | X10: =V10-W10 -> 0 | Y10: =MIN(O10,I10-W10) -> 1058983.1 | Z10: =MIN(N10,I10-W10-Y10) -> 0 | AA10: =MIN(M10,I10-W10-Y10-Z10) -> 0 | AB10: =MIN(L10,I10-W10-Y10-Z10-AA10) -> 0 | AC10: =L10-AB10 -> 2.2289869e+08 | AD10: =N10-Z10 -> 15889260 | AE10: =M10-AA10 -> 38134224 | AF10: =O10-Y10 -> 5096463.2 | AG10: =F10+E10+H10+W10 -> 9943837.4 | AH10: =MIN(AC10,AG10) -> 9943837.4 | AI10: =MIN(AE10,AG10-AH10) -> 0 | AJ10: =MIN(AD10,AG10-AH10-AI10) -> 0 | AK10: =MIN(AF10,AG10-AH10-AI10-AJ10) -> 0 | AL10: =AC10-AH10 -> 2.1295486e+08 | AM10: =AE10-AI10 -> 38134224 | AN10: =AD10-AJ10 -> 15889260 | AO10: =AF10-AK10 -> 5096463.2 | AP10: =D10-E10-F10 -> 2.720748e+08 | AQ10: =SUM(AL10:AO10)-AP10 -> 0 | AR10: =SUMIFS(Python_Results!$C$2:$C$217,Python_Results!$A$2:$A$217,Assumptions!$B$10,Python_Results!$B$2:$B$217,A10) -> 2.720748e+08 | AS10: =SUMIFS(Python_Results!$D$2:$D$217,Python_Results!$A$2:$A$217,Assumptions!$B$10,Python_Results!$B$2:$B$217,A10) -> 2.1295486e+08 | AT10: =SUMIFS(Python_Results!$E$2:$E$217,Python_Results!$A$2:$A$217,Assumptions!$B$10,Python_Results!$B$2:$B$217,A10) -> 38134224 | AU10: =SUMIFS(Python_Results!$F$2:$F$217,Python_Results!$A$2:$A$217,Assumptions!$B$10,Python_Results!$B$2:$B$217,A10) -> 15889260 | AV10: =SUMIFS(Python_Results!$G$2:$G$217,Python_Results!$A$2:$A$217,Assumptions!$B$10,Python_Results!$B$2:$B$217,A10) -> 5096463.2 | AW10: =AP10-AR10 -> -0.0031737685 | AX10: =AL10-AS10 -> -0.0014253259 | AY10: =AM10-AT10 -> -0.003200002 | AZ10: =AN10-AU10 -> -0.0029999986 | BA10: =AO10-AV10 -> 0.0044515999
A11: 5 | B11: =AP10 -> 2.720748e+08 | C11: =B11*Assumptions!$B$14 -> 3015630.8 | D11: =B11-C11 -> 2.6905917e+08 | E11: =D11*Assumptions!$B$15 -> 1203619.9 | F11: =(D11-E11)/MAX(Assumptions!$B$7-A11+1,1) -> 6510390 | G11: =D11*Assumptions!$B$6/12 -> 2454145 | H11: =C11*(1-Assumptions!$B$13) -> 1312704.1 | I11: =C11*Assumptions!$B$13 -> 1702926.7 | J11: =B11*Assumptions!$B$9/12 -> 113364.5 | K11: =MAX(G11-J11,0) -> 2340780.5 | L11: =AL10 -> 2.1295486e+08 | M11: =AM10 -> 38134224 | N11: =AN10 -> 15889260 | O11: =AO10 -> 5096463.2 | P11: =L11*Assumptions!$C$27/12 -> 1242236.7 | Q11: =M11*Assumptions!$C$28/12 -> 270117.42 | R11: =N11*Assumptions!$C$29/12 -> 152272.08 | S11: =MIN(P11,K11) -> 1242236.7 | T11: =MIN(Q11,K11-S11) -> 270117.42 | U11: =MIN(R11,K11-S11-T11) -> 152272.08 | V11: =K11-S11-T11-U11 -> 676154.3 | W11: =MIN(V11,I11) -> 676154.3 | X11: =V11-W11 -> 0 | Y11: =MIN(O11,I11-W11) -> 1026772.4 | Z11: =MIN(N11,I11-W11-Y11) -> 0 | AA11: =MIN(M11,I11-W11-Y11-Z11) -> 0 | AB11: =MIN(L11,I11-W11-Y11-Z11-AA11) -> 0 | AC11: =L11-AB11 -> 2.1295486e+08 | AD11: =N11-Z11 -> 15889260 | AE11: =M11-AA11 -> 38134224 | AF11: =O11-Y11 -> 4069690.8 | AG11: =F11+E11+H11+W11 -> 9702868.3 | AH11: =MIN(AC11,AG11) -> 9702868.3 | AI11: =MIN(AE11,AG11-AH11) -> 0 | AJ11: =MIN(AD11,AG11-AH11-AI11) -> 0 | AK11: =MIN(AF11,AG11-AH11-AI11-AJ11) -> 0 | AL11: =AC11-AH11 -> 2.0325199e+08 | AM11: =AE11-AI11 -> 38134224 | AN11: =AD11-AJ11 -> 15889260 | AO11: =AF11-AK11 -> 4069690.8 | AP11: =D11-E11-F11 -> 2.6134516e+08 | AQ11: =SUM(AL11:AO11)-AP11 -> 0 | AR11: =SUMIFS(Python_Results!$C$2:$C$217,Python_Results!$A$2:$A$217,Assumptions!$B$10,Python_Results!$B$2:$B$217,A11) -> 2.6134516e+08 | AS11: =SUMIFS(Python_Results!$D$2:$D$217,Python_Results!$A$2:$A$217,Assumptions!$B$10,Python_Results!$B$2:$B$217,A11) -> 2.0325199e+08 | AT11: =SUMIFS(Python_Results!$E$2:$E$217,Python_Results!$A$2:$A$217,Assumptions!$B$10,Python_Results!$B$2:$B$217,A11) -> 38134224 | AU11: =SUMIFS(Python_Results!$F$2:$F$217,Python_Results!$A$2:$A$217,Assumptions!$B$10,Python_Results!$B$2:$B$217,A11) -> 15889260 | AV11: =SUMIFS(Python_Results!$G$2:$G$217,Python_Results!$A$2:$A$217,Assumptions!$B$10,Python_Results!$B$2:$B$217,A11) -> 4069690.8 | AW11: =AP11-AR11 -> -0.00049972534 | AX11: =AL11-AS11 -> 0.0025110245 | AY11: =AM11-AT11 -> -0.003200002 | AZ11: =AN11-AU11 -> -0.0029999986 | BA11: =AO11-AV11 -> 0.003189248
A12: 6 | B12: =AP11 -> 2.6134516e+08 | C12: =B12*Assumptions!$B$14 -> 2896705.3 | D12: =B12-C12 -> 2.5844846e+08 | E12: =D12*Assumptions!$B$15 -> 1156153.5 | F12: =(D12-E12)/MAX(Assumptions!$B$7-A12+1,1) -> 6409428.9 | G12: =D12*Assumptions!$B$6/12 -> 2357362.4 | H12: =C12*(1-Assumptions!$B$13) -> 1260935.8 | I12: =C12*Assumptions!$B$13 -> 1635769.5 | J12: =B12*Assumptions!$B$9/12 -> 108893.82 | K12: =MAX(G12-J12,0) -> 2248468.6 | L12: =AL11 -> 2.0325199e+08 | M12: =AM11 -> 38134224 | N12: =AN11 -> 15889260 | O12: =AO11 -> 4069690.8 | P12: =L12*Assumptions!$C$27/12 -> 1185636.6 | Q12: =M12*Assumptions!$C$28/12 -> 270117.42 | R12: =N12*Assumptions!$C$29/12 -> 152272.08 | S12: =MIN(P12,K12) -> 1185636.6 | T12: =MIN(Q12,K12-S12) -> 270117.42 | U12: =MIN(R12,K12-S12-T12) -> 152272.08 | V12: =K12-S12-T12-U12 -> 640442.5 | W12: =MIN(V12,I12) -> 640442.5 | X12: =V12-W12 -> 0 | Y12: =MIN(O12,I12-W12) -> 995327 | Z12: =MIN(N12,I12-W12-Y12) -> 0 | AA12: =MIN(M12,I12-W12-Y12-Z12) -> 0 | AB12: =MIN(L12,I12-W12-Y12-Z12-AA12) -> 0 | AC12: =L12-AB12 -> 2.0325199e+08 | AD12: =N12-Z12 -> 15889260 | AE12: =M12-AA12 -> 38134224 | AF12: =O12-Y12 -> 3074363.8 | AG12: =F12+E12+H12+W12 -> 9466960.7 | AH12: =MIN(AC12,AG12) -> 9466960.7 | AI12: =MIN(AE12,AG12-AH12) -> 0 | AJ12: =MIN(AD12,AG12-AH12-AI12) -> 0 | AK12: =MIN(AF12,AG12-AH12-AI12-AJ12) -> 0 | AL12: =AC12-AH12 -> 1.9378503e+08 | AM12: =AE12-AI12 -> 38134224 | AN12: =AD12-AJ12 -> 15889260 | AO12: =AF12-AK12 -> 3074363.8 | AP12: =D12-E12-F12 -> 2.5088287e+08 | AQ12: =SUM(AL12:AO12)-AP12 -> 0 | AR12: =SUMIFS(Python_Results!$C$2:$C$217,Python_Results!$A$2:$A$217,Assumptions!$B$10,Python_Results!$B$2:$B$217,A12) -> 2.5088287e+08 | AS12: =SUMIFS(Python_Results!$D$2:$D$217,Python_Results!$A$2:$A$217,Assumptions!$B$10,Python_Results!$B$2:$B$217,A12) -> 1.9378503e+08 | AT12: =SUMIFS(Python_Results!$E$2:$E$217,Python_Results!$A$2:$A$217,Assumptions!$B$10,Python_Results!$B$2:$B$217,A12) -> 38134224 | AU12: =SUMIFS(Python_Results!$F$2:$F$217,Python_Results!$A$2:$A$217,Assumptions!$B$10,Python_Results!$B$2:$B$217,A12) -> 15889260 | AV12: =SUMIFS(Python_Results!$G$2:$G$217,Python_Results!$A$2:$A$217,Assumptions!$B$10,Python_Results!$B$2:$B$217,A12) -> 3074363.8 | AW12: =AP12-AR12 -> 0.0021422803 | AX12: =AL12-AS12 -> 0.0024033189 | AY12: =AM12-AT12 -> -0.003200002 | AZ12: =AN12-AU12 -> -0.0029999986 | BA12: =AO12-AV12 -> -0.0040610321
A13: 7 | B13: =AP12 -> 2.5088287e+08 | C13: =B13*Assumptions!$B$14 -> 2780743.1 | D13: =B13-C13 -> 2.4810213e+08 | E13: =D13*Assumptions!$B$15 -> 1109869.8 | F13: =(D13-E13)/MAX(Assumptions!$B$7-A13+1,1) -> 6310033.5 | G13: =D13*Assumptions!$B$6/12 -> 2262991.4 | H13: =C13*(1-Assumptions!$B$13) -> 1210457.5 | I13: =C13*Assumptions!$B$13 -> 1570285.6 | J13: =B13*Assumptions!$B$9/12 -> 104534.53 | K13: =MAX(G13-J13,0) -> 2158456.9 | L13: =AL12 -> 1.9378503e+08 | M13: =AM12 -> 38134224 | N13: =AN12 -> 15889260 | O13: =AO12 -> 3074363.8 | P13: =L13*Assumptions!$C$27/12 -> 1130412.7 | Q13: =M13*Assumptions!$C$28/12 -> 270117.42 | R13: =N13*Assumptions!$C$29/12 -> 152272.08 | S13: =MIN(P13,K13) -> 1130412.7 | T13: =MIN(Q13,K13-S13) -> 270117.42 | U13: =MIN(R13,K13-S13-T13) -> 152272.08 | V13: =K13-S13-T13-U13 -> 605654.73 | W13: =MIN(V13,I13) -> 605654.73 | X13: =V13-W13 -> 0 | Y13: =MIN(O13,I13-W13) -> 964630.91 | Z13: =MIN(N13,I13-W13-Y13) -> 0 | AA13: =MIN(M13,I13-W13-Y13-Z13) -> 0 | AB13: =MIN(L13,I13-W13-Y13-Z13-AA13) -> 0 | AC13: =L13-AB13 -> 1.9378503e+08 | AD13: =N13-Z13 -> 15889260 | AE13: =M13-AA13 -> 38134224 | AF13: =O13-Y13 -> 2109732.9 | AG13: =F13+E13+H13+W13 -> 9236015.5 | AH13: =MIN(AC13,AG13) -> 9236015.5 | AI13: =MIN(AE13,AG13-AH13) -> 0 | AJ13: =MIN(AD13,AG13-AH13-AI13) -> 0 | AK13: =MIN(AF13,AG13-AH13-AI13-AJ13) -> 0 | AL13: =AC13-AH13 -> 1.8454901e+08 | AM13: =AE13-AI13 -> 38134224 | AN13: =AD13-AJ13 -> 15889260 | AO13: =AF13-AK13 -> 2109732.9 | AP13: =D13-E13-F13 -> 2.4068223e+08 | AQ13: =SUM(AL13:AO13)-AP13 -> 0 | AR13: =SUMIFS(Python_Results!$C$2:$C$217,Python_Results!$A$2:$A$217,Assumptions!$B$10,Python_Results!$B$2:$B$217,A13) -> 2.4068223e+08 | AS13: =SUMIFS(Python_Results!$D$2:$D$217,Python_Results!$A$2:$A$217,Assumptions!$B$10,Python_Results!$B$2:$B$217,A13) -> 1.8454901e+08 | AT13: =SUMIFS(Python_Results!$E$2:$E$217,Python_Results!$A$2:$A$217,Assumptions!$B$10,Python_Results!$B$2:$B$217,A13) -> 38134224 | AU13: =SUMIFS(Python_Results!$F$2:$F$217,Python_Results!$A$2:$A$217,Assumptions!$B$10,Python_Results!$B$2:$B$217,A13) -> 15889260 | AV13: =SUMIFS(Python_Results!$G$2:$G$217,Python_Results!$A$2:$A$217,Assumptions!$B$10,Python_Results!$B$2:$B$217,A13) -> 2109732.9 | AW13: =AP13-AR13 -> -0.004437983 | AX13: =AL13-AS13 -> 0.0025932193 | AY13: =AM13-AT13 -> -0.003200002 | AZ13: =AN13-AU13 -> -0.0029999986 | BA13: =AO13-AV13 -> -0.00083119702
A14: 8 | B14: =AP13 -> 2.4068223e+08 | C14: =B14*Assumptions!$B$14 -> 2667680.9 | D14: =B14-C14 -> 2.3801455e+08 | E14: =D14*Assumptions!$B$15 -> 1064743.6 | F14: =(D14-E14)/MAX(Assumptions!$B$7-A14+1,1) -> 6212179.5 | G14: =D14*Assumptions!$B$6/12 -> 2170980.4 | H14: =C14*(1-Assumptions!$B$13) -> 1161241.5 | I14: =C14*Assumptions!$B$13 -> 1506439.4 | J14: =B14*Assumptions!$B$9/12 -> 100284.26 | K14: =MAX(G14-J14,0) -> 2070696.2 | L14: =AL13 -> 1.8454901e+08 | M14: =AM13 -> 38134224 | N14: =AN13 -> 15889260 | O14: =AO13 -> 2109732.9 | P14: =L14*Assumptions!$C$27/12 -> 1076535.9 | Q14: =M14*Assumptions!$C$28/12 -> 270117.42 | R14: =N14*Assumptions!$C$29/12 -> 152272.08 | S14: =MIN(P14,K14) -> 1076535.9 | T14: =MIN(Q14,K14-S14) -> 270117.42 | U14: =MIN(R14,K14-S14-T14) -> 152272.08 | V14: =K14-S14-T14-U14 -> 571770.79 | W14: =MIN(V14,I14) -> 571770.79 | X14: =V14-W14 -> 0 | Y14: =MIN(O14,I14-W14) -> 934668.6 | Z14: =MIN(N14,I14-W14-Y14) -> 0 | AA14: =MIN(M14,I14-W14-Y14-Z14) -> 0 | AB14: =MIN(L14,I14-W14-Y14-Z14-AA14) -> 0 | AC14: =L14-AB14 -> 1.8454901e+08 | AD14: =N14-Z14 -> 15889260 | AE14: =M14-AA14 -> 38134224 | AF14: =O14-Y14 -> 1175064.3 | AG14: =F14+E14+H14+W14 -> 9009935.4 | AH14: =MIN(AC14,AG14) -> 9009935.4 | AI14: =MIN(AE14,AG14-AH14) -> 0 | AJ14: =MIN(AD14,AG14-AH14-AI14) -> 0 | AK14: =MIN(AF14,AG14-AH14-AI14-AJ14) -> 0 | AL14: =AC14-AH14 -> 1.7553908e+08 | AM14: =AE14-AI14 -> 38134224 | AN14: =AD14-AJ14 -> 15889260 | AO14: =AF14-AK14 -> 1175064.3 | AP14: =D14-E14-F14 -> 2.3073762e+08 | AQ14: =SUM(AL14:AO14)-AP14 -> 0 | AR14: =SUMIFS(Python_Results!$C$2:$C$217,Python_Results!$A$2:$A$217,Assumptions!$B$10,Python_Results!$B$2:$B$217,A14) -> 2.3073762e+08 | AS14: =SUMIFS(Python_Results!$D$2:$D$217,Python_Results!$A$2:$A$217,Assumptions!$B$10,Python_Results!$B$2:$B$217,A14) -> 1.7553908e+08 | AT14: =SUMIFS(Python_Results!$E$2:$E$217,Python_Results!$A$2:$A$217,Assumptions!$B$10,Python_Results!$B$2:$B$217,A14) -> 38134224 | AU14: =SUMIFS(Python_Results!$F$2:$F$217,Python_Results!$A$2:$A$217,Assumptions!$B$10,Python_Results!$B$2:$B$217,A14) -> 15889260 | AV14: =SUMIFS(Python_Results!$G$2:$G$217,Python_Results!$A$2:$A$217,Assumptions!$B$10,Python_Results!$B$2:$B$217,A14) -> 1175064.3 | AW14: =AP14-AR14 -> -0.0042271614 | AX14: =AL14-AS14 -> -0.0039083958 | AY14: =AM14-AT14 -> -0.003200002 | AZ14: =AN14-AU14 -> -0.0029999986 | BA14: =AO14-AV14 -> -0.0041187613
A15: 9 | B15: =AP14 -> 2.3073762e+08 | C15: =B15*Assumptions!$B$14 -> 2557456.6 | D15: =B15-C15 -> 2.2818017e+08 | E15: =D15*Assumptions!$B$15 -> 1020750.1 | F15: =(D15-E15)/MAX(Assumptions!$B$7-A15+1,1) -> 6115843 | G15: =D15*Assumptions!$B$6/12 -> 2081279 | H15: =C15*(1-Assumptions!$B$13) -> 1113260.8 | I15: =C15*Assumptions!$B$13 -> 1444195.7 | J15: =B15*Assumptions!$B$9/12 -> 96140.677 | K15: =MAX(G15-J15,0) -> 1985138.3 | L15: =AL14 -> 1.7553908e+08 | M15: =AM14 -> 38134224 | N15: =AN14 -> 15889260 | O15: =AO14 -> 1175064.3 | P15: =L15*Assumptions!$C$27/12 -> 1023977.9 | Q15: =M15*Assumptions!$C$28/12 -> 270117.42 | R15: =N15*Assumptions!$C$29/12 -> 152272.08 | S15: =MIN(P15,K15) -> 1023977.9 | T15: =MIN(Q15,K15-S15) -> 270117.42 | U15: =MIN(R15,K15-S15-T15) -> 152272.08 | V15: =K15-S15-T15-U15 -> 538770.9 | W15: =MIN(V15,I15) -> 538770.9 | X15: =V15-W15 -> 0 | Y15: =MIN(O15,I15-W15) -> 905424.83 | Z15: =MIN(N15,I15-W15-Y15) -> 0 | AA15: =MIN(M15,I15-W15-Y15-Z15) -> 0 | AB15: =MIN(L15,I15-W15-Y15-Z15-AA15) -> 0 | AC15: =L15-AB15 -> 1.7553908e+08 | AD15: =N15-Z15 -> 15889260 | AE15: =M15-AA15 -> 38134224 | AF15: =O15-Y15 -> 269639.42 | AG15: =F15+E15+H15+W15 -> 8788624.8 | AH15: =MIN(AC15,AG15) -> 8788624.8 | AI15: =MIN(AE15,AG15-AH15) -> 0 | AJ15: =MIN(AD15,AG15-AH15-AI15) -> 0 | AK15: =MIN(AF15,AG15-AH15-AI15-AJ15) -> 0 | AL15: =AC15-AH15 -> 1.6675045e+08 | AM15: =AE15-AI15 -> 38134224 | AN15: =AD15-AJ15 -> 15889260 | AO15: =AF15-AK15 -> 269639.42 | AP15: =D15-E15-F15 -> 2.2104357e+08 | AQ15: =SUM(AL15:AO15)-AP15 -> 0 | AR15: =SUMIFS(Python_Results!$C$2:$C$217,Python_Results!$A$2:$A$217,Assumptions!$B$10,Python_Results!$B$2:$B$217,A15) -> 2.2104357e+08 | AS15: =SUMIFS(Python_Results!$D$2:$D$217,Python_Results!$A$2:$A$217,Assumptions!$B$10,Python_Results!$B$2:$B$217,A15) -> 1.6675045e+08 | AT15: =SUMIFS(Python_Results!$E$2:$E$217,Python_Results!$A$2:$A$217,Assumptions!$B$10,Python_Results!$B$2:$B$217,A15) -> 38134224 | AU15: =SUMIFS(Python_Results!$F$2:$F$217,Python_Results!$A$2:$A$217,Assumptions!$B$10,Python_Results!$B$2:$B$217,A15) -> 15889260 | AV15: =SUMIFS(Python_Results!$G$2:$G$217,Python_Results!$A$2:$A$217,Assumptions!$B$10,Python_Results!$B$2:$B$217,A15) -> 269639.42 | AW15: =AP15-AR15 -> -0.0026575625 | AX15: =AL15-AS15 -> 0.00092640519 | AY15: =AM15-AT15 -> -0.003200002 | AZ15: =AN15-AU15 -> -0.0029999986 | BA15: =AO15-AV15 -> 0.0026160232
A16: 10 | B16: =AP15 -> 2.2104357e+08 | C16: =B16*Assumptions!$B$14 -> 2450009.4 | D16: =B16-C16 -> 2.1859357e+08 | E16: =D16*Assumptions!$B$15 -> 977865.05 | F16: =(D16-E16)/MAX(Assumptions!$B$7-A16+1,1) -> 6021000.4 | G16: =D16*Assumptions!$B$6/12 -> 1993837.6 | H16: =C16*(1-Assumptions!$B$13) -> 1066489.1 | I16: =C16*Assumptions!$B$13 -> 1383520.3 | J16: =B16*Assumptions!$B$9/12 -> 92101.489 | K16: =MAX(G16-J16,0) -> 1901736.1 | L16: =AL15 -> 1.6675045e+08 | M16: =AM15 -> 38134224 | N16: =AN15 -> 15889260 | O16: =AO15 -> 269639.42 | P16: =L16*Assumptions!$C$27/12 -> 972710.96 | Q16: =M16*Assumptions!$C$28/12 -> 270117.42 | R16: =N16*Assumptions!$C$29/12 -> 152272.08 | S16: =MIN(P16,K16) -> 972710.96 | T16: =MIN(Q16,K16-S16) -> 270117.42 | U16: =MIN(R16,K16-S16-T16) -> 152272.08 | V16: =K16-S16-T16-U16 -> 506635.66 | W16: =MIN(V16,I16) -> 506635.66 | X16: =V16-W16 -> 0 | Y16: =MIN(O16,I16-W16) -> 269639.42 | Z16: =MIN(N16,I16-W16-Y16) -> 607245.22 | AA16: =MIN(M16,I16-W16-Y16-Z16) -> 0 | AB16: =MIN(L16,I16-W16-Y16-Z16-AA16) -> 0 | AC16: =L16-AB16 -> 1.6675045e+08 | AD16: =N16-Z16 -> 15282015 | AE16: =M16-AA16 -> 38134224 | AF16: =O16-Y16 -> 0 | AG16: =F16+E16+H16+W16 -> 8571990.2 | AH16: =MIN(AC16,AG16) -> 8571990.2 | AI16: =MIN(AE16,AG16-AH16) -> 0 | AJ16: =MIN(AD16,AG16-AH16-AI16) -> 0 | AK16: =MIN(AF16,AG16-AH16-AI16-AJ16) -> 0 | AL16: =AC16-AH16 -> 1.5817846e+08 | AM16: =AE16-AI16 -> 38134224 | AN16: =AD16-AJ16 -> 15282015 | AO16: =AF16-AK16 -> 0 | AP16: =D16-E16-F16 -> 2.115947e+08 | AQ16: =SUM(AL16:AO16)-AP16 -> 0 | AR16: =SUMIFS(Python_Results!$C$2:$C$217,Python_Results!$A$2:$A$217,Assumptions!$B$10,Python_Results!$B$2:$B$217,A16) -> 2.115947e+08 | AS16: =SUMIFS(Python_Results!$D$2:$D$217,Python_Results!$A$2:$A$217,Assumptions!$B$10,Python_Results!$B$2:$B$217,A16) -> 1.5817846e+08 | AT16: =SUMIFS(Python_Results!$E$2:$E$217,Python_Results!$A$2:$A$217,Assumptions!$B$10,Python_Results!$B$2:$B$217,A16) -> 38134224 | AU16: =SUMIFS(Python_Results!$F$2:$F$217,Python_Results!$A$2:$A$217,Assumptions!$B$10,Python_Results!$B$2:$B$217,A16) -> 15282015 | AV16: =SUMIFS(Python_Results!$G$2:$G$217,Python_Results!$A$2:$A$217,Assumptions!$B$10,Python_Results!$B$2:$B$217,A16) -> 0 | AW16: =AP16-AR16 -> -0.0044376552 | AX16: =AL16-AS16 -> -0.00034290552 | AY16: =AM16-AT16 -> -0.003200002 | AZ16: =AN16-AU16 -> -0.0008947812 | BA16: =AO16-AV16 -> 0
A17: 11 | B17: =AP16 -> 2.115947e+08 | C17: =B17*Assumptions!$B$14 -> 2345279.7 | D17: =B17-C17 -> 2.0924942e+08 | E17: =D17*Assumptions!$B$15 -> 936064.58 | F17: =(D17-E17)/MAX(Assumptions!$B$7-A17+1,1) -> 5927628.6 | G17: =D17*Assumptions!$B$6/12 -> 1908607.7 | H17: =C17*(1-Assumptions!$B$13) -> 1020900.2 | I17: =C17*Assumptions!$B$13 -> 1324379.4 | J17: =B17*Assumptions!$B$9/12 -> 88164.458 | K17: =MAX(G17-J17,0) -> 1820443.2 | L17: =AL16 -> 1.5817846e+08 | M17: =AM16 -> 38134224 | N17: =AN16 -> 15282015 | O17: =AO16 -> 0 | P17: =L17*Assumptions!$C$27/12 -> 922707.69 | Q17: =M17*Assumptions!$C$28/12 -> 270117.42 | R17: =N17*Assumptions!$C$29/12 -> 146452.64 | S17: =MIN(P17,K17) -> 922707.69 | T17: =MIN(Q17,K17-S17) -> 270117.42 | U17: =MIN(R17,K17-S17-T17) -> 146452.64 | V17: =K17-S17-T17-U17 -> 481165.5 | W17: =MIN(V17,I17) -> 481165.5 | X17: =V17-W17 -> 0 | Y17: =MIN(O17,I17-W17) -> 0 | Z17: =MIN(N17,I17-W17-Y17) -> 843213.93 | AA17: =MIN(M17,I17-W17-Y17-Z17) -> 0 | AB17: =MIN(L17,I17-W17-Y17-Z17-AA17) -> 0 | AC17: =L17-AB17 -> 1.5817846e+08 | AD17: =N17-Z17 -> 14438801 | AE17: =M17-AA17 -> 38134224 | AF17: =O17-Y17 -> 0 | AG17: =F17+E17+H17+W17 -> 8365758.9 | AH17: =MIN(AC17,AG17) -> 8365758.9 | AI17: =MIN(AE17,AG17-AH17) -> 0 | AJ17: =MIN(AD17,AG17-AH17-AI17) -> 0 | AK17: =MIN(AF17,AG17-AH17-AI17-AJ17) -> 0 | AL17: =AC17-AH17 -> 1.498127e+08 | AM17: =AE17-AI17 -> 38134224 | AN17: =AD17-AJ17 -> 14438801 | AO17: =AF17-AK17 -> 0 | AP17: =D17-E17-F17 -> 2.0238573e+08 | AQ17: =SUM(AL17:AO17)-AP17 -> 0 | AR17: =SUMIFS(Python_Results!$C$2:$C$217,Python_Results!$A$2:$A$217,Assumptions!$B$10,Python_Results!$B$2:$B$217,A17) -> 2.0238573e+08 | AS17: =SUMIFS(Python_Results!$D$2:$D$217,Python_Results!$A$2:$A$217,Assumptions!$B$10,Python_Results!$B$2:$B$217,A17) -> 1.498127e+08 | AT17: =SUMIFS(Python_Results!$E$2:$E$217,Python_Results!$A$2:$A$217,Assumptions!$B$10,Python_Results!$B$2:$B$217,A17) -> 38134224 | AU17: =SUMIFS(Python_Results!$F$2:$F$217,Python_Results!$A$2:$A$217,Assumptions!$B$10,Python_Results!$B$2:$B$217,A17) -> 14438801 | AV17: =SUMIFS(Python_Results!$G$2:$G$217,Python_Results!$A$2:$A$217,Assumptions!$B$10,Python_Results!$B$2:$B$217,A17) -> 0 | AW17: =AP17-AR17 -> -0.0032571256 | AX17: =AL17-AS17 -> -0.0018733442 | AY17: =AM17-AT17 -> -0.003200002 | AZ17: =AN17-AU17 -> 0.0018161945 | BA17: =AO17-AV17 -> 0
A18: 12 | B18: =AP17 -> 2.0238573e+08 | C18: =B18*Assumptions!$B$14 -> 2243209 | D18: =B18-C18 -> 2.0014252e+08 | E18: =D18*Assumptions!$B$15 -> 895325.41 | F18: =(D18-E18)/MAX(Assumptions!$B$7-A18+1,1) -> 5835704.8 | G18: =D18*Assumptions!$B$6/12 -> 1825541.7 | H18: =C18*(1-Assumptions!$B$13) -> 976468.87 | I18: =C18*Assumptions!$B$13 -> 1266740.1 | J18: =B18*Assumptions!$B$9/12 -> 84327.386 | K18: =MAX(G18-J18,0) -> 1741214.4 | L18: =AL17 -> 1.498127e+08 | M18: =AM17 -> 38134224 | N18: =AN17 -> 14438801 | O18: =AO17 -> 0 | P18: =L18*Assumptions!$C$27/12 -> 873907.43 | Q18: =M18*Assumptions!$C$28/12 -> 270117.42 | R18: =N18*Assumptions!$C$29/12 -> 138371.84 | S18: =MIN(P18,K18) -> 873907.43 | T18: =MIN(Q18,K18-S18) -> 270117.42 | U18: =MIN(R18,K18-S18-T18) -> 138371.84 | V18: =K18-S18-T18-U18 -> 458817.67 | W18: =MIN(V18,I18) -> 458817.67 | X18: =V18-W18 -> 0 | Y18: =MIN(O18,I18-W18) -> 0 | Z18: =MIN(N18,I18-W18-Y18) -> 807922.44 | AA18: =MIN(M18,I18-W18-Y18-Z18) -> 0 | AB18: =MIN(L18,I18-W18-Y18-Z18-AA18) -> 0 | AC18: =L18-AB18 -> 1.498127e+08 | AD18: =N18-Z18 -> 13630879 | AE18: =M18-AA18 -> 38134224 | AF18: =O18-Y18 -> 0 | AG18: =F18+E18+H18+W18 -> 8166316.7 | AH18: =MIN(AC18,AG18) -> 8166316.7 | AI18: =MIN(AE18,AG18-AH18) -> 0 | AJ18: =MIN(AD18,AG18-AH18-AI18) -> 0 | AK18: =MIN(AF18,AG18-AH18-AI18-AJ18) -> 0 | AL18: =AC18-AH18 -> 1.4164638e+08 | AM18: =AE18-AI18 -> 38134224 | AN18: =AD18-AJ18 -> 13630879 | AO18: =AF18-AK18 -> 0 | AP18: =D18-E18-F18 -> 1.9341149e+08 | AQ18: =SUM(AL18:AO18)-AP18 -> 0 | AR18: =SUMIFS(Python_Results!$C$2:$C$217,Python_Results!$A$2:$A$217,Assumptions!$B$10,Python_Results!$B$2:$B$217,A18) -> 1.9341149e+08 | AS18: =SUMIFS(Python_Results!$D$2:$D$217,Python_Results!$A$2:$A$217,Assumptions!$B$10,Python_Results!$B$2:$B$217,A18) -> 1.4164638e+08 | AT18: =SUMIFS(Python_Results!$E$2:$E$217,Python_Results!$A$2:$A$217,Assumptions!$B$10,Python_Results!$B$2:$B$217,A18) -> 38134224 | AU18: =SUMIFS(Python_Results!$F$2:$F$217,Python_Results!$A$2:$A$217,Assumptions!$B$10,Python_Results!$B$2:$B$217,A18) -> 13630879 | AV18: =SUMIFS(Python_Results!$G$2:$G$217,Python_Results!$A$2:$A$217,Assumptions!$B$10,Python_Results!$B$2:$B$217,A18) -> 0 | AW18: =AP18-AR18 -> -0.0040459037 | AX18: =AL18-AS18 -> 0.0027319491 | AY18: =AM18-AT18 -> -0.003200002 | AZ18: =AN18-AU18 -> -0.0035778843 | BA18: =AO18-AV18 -> 0
A19: 13 | B19: =AP18 -> 1.9341149e+08 | C19: =B19*Assumptions!$B$14 -> 2143740 | D19: =B19-C19 -> 1.9126775e+08 | E19: =D19*Assumptions!$B$15 -> 855624.66 | F19: =(D19-E19)/MAX(Assumptions!$B$7-A19+1,1) -> 5745206.5 | G19: =D19*Assumptions!$B$6/12 -> 1744593.1 | H19: =C19*(1-Assumptions!$B$13) -> 933170.04 | I19: =C19*Assumptions!$B$13 -> 1210570 | J19: =B19*Assumptions!$B$9/12 -> 80588.12 | K19: =MAX(G19-J19,0) -> 1664005 | L19: =AL18 -> 1.4164638e+08 | M19: =AM18 -> 38134224 | N19: =AN18 -> 13630879 | O19: =AO18 -> 0 | P19: =L19*Assumptions!$C$27/12 -> 826270.58 | Q19: =M19*Assumptions!$C$28/12 -> 270117.42 | R19: =N19*Assumptions!$C$29/12 -> 130629.25 | S19: =MIN(P19,K19) -> 826270.58 | T19: =MIN(Q19,K19-S19) -> 270117.42 | U19: =MIN(R19,K19-S19-T19) -> 130629.25 | V19: =K19-S19-T19-U19 -> 436987.74 | W19: =MIN(V19,I19) -> 436987.74 | X19: =V19-W19 -> 0 | Y19: =MIN(O19,I19-W19) -> 0 | Z19: =MIN(N19,I19-W19-Y19) -> 773582.26 | AA19: =MIN(M19,I19-W19-Y19-Z19) -> 0 | AB19: =MIN(L19,I19-W19-Y19-Z19-AA19) -> 0 | AC19: =L19-AB19 -> 1.4164638e+08 | AD19: =N19-Z19 -> 12857296 | AE19: =M19-AA19 -> 38134224 | AF19: =O19-Y19 -> 0 | AG19: =F19+E19+H19+W19 -> 7970988.9 | AH19: =MIN(AC19,AG19) -> 7970988.9 | AI19: =MIN(AE19,AG19-AH19) -> 0 | AJ19: =MIN(AD19,AG19-AH19-AI19) -> 0 | AK19: =MIN(AF19,AG19-AH19-AI19-AJ19) -> 0 | AL19: =AC19-AH19 -> 1.336754e+08 | AM19: =AE19-AI19 -> 38134224 | AN19: =AD19-AJ19 -> 12857296 | AO19: =AF19-AK19 -> 0 | AP19: =D19-E19-F19 -> 1.8466692e+08 | AQ19: =SUM(AL19:AO19)-AP19 -> 0 | AR19: =SUMIFS(Python_Results!$C$2:$C$217,Python_Results!$A$2:$A$217,Assumptions!$B$10,Python_Results!$B$2:$B$217,A19) -> 1.8466692e+08 | AS19: =SUMIFS(Python_Results!$D$2:$D$217,Python_Results!$A$2:$A$217,Assumptions!$B$10,Python_Results!$B$2:$B$217,A19) -> 1.336754e+08 | AT19: =SUMIFS(Python_Results!$E$2:$E$217,Python_Results!$A$2:$A$217,Assumptions!$B$10,Python_Results!$B$2:$B$217,A19) -> 38134224 | AU19: =SUMIFS(Python_Results!$F$2:$F$217,Python_Results!$A$2:$A$217,Assumptions!$B$10,Python_Results!$B$2:$B$217,A19) -> 12857296 | AV19: =SUMIFS(Python_Results!$G$2:$G$217,Python_Results!$A$2:$A$217,Assumptions!$B$10,Python_Results!$B$2:$B$217,A19) -> 0 | AW19: =AP19-AR19 -> 0.0015434921 | AX19: =AL19-AS19 -> 0.0036922842 | AY19: =AM19-AT19 -> -0.003200002 | AZ19: =AN19-AU19 -> 0.0010511857 | BA19: =AO19-AV19 -> 0
... A42: 36 | B42: =AP41 -> 41317493 | C42: =B42*Assumptions!$B$14 -> 457956.06 | D42: =B42-C42 -> 40859537 | E42: =D42*Assumptions!$B$15 -> 182782.66 | F42: =(D42-E42)/MAX(Assumptions!$B$7-A42+1,1) -> 4010414.2 | G42: =D42*Assumptions!$B$6/12 -> 372688.38 | H42: =C42*(1-Assumptions!$B$13) -> 199348.27 | I42: =C42*Assumptions!$B$13 -> 258607.79 | J42: =B42*Assumptions!$B$9/12 -> 17215.622 | K42: =MAX(G42-J42,0) -> 355472.75 | L42: =AL41 -> 334968.95 | M42: =AM41 -> 38134224 | N42: =AN41 -> 2848299.5 | O42: =AO41 -> 0 | P42: =L42*Assumptions!$C$27/12 -> 1953.9856 | Q42: =M42*Assumptions!$C$28/12 -> 270117.42 | R42: =N42*Assumptions!$C$29/12 -> 27296.204 | S42: =MIN(P42,K42) -> 1953.9856 | T42: =MIN(Q42,K42-S42) -> 270117.42 | U42: =MIN(R42,K42-S42-T42) -> 27296.204 | V42: =K42-S42-T42-U42 -> 56105.143 | W42: =MIN(V42,I42) -> 56105.143 | X42: =V42-W42 -> 0 | Y42: =MIN(O42,I42-W42) -> 0 | Z42: =MIN(N42,I42-W42-Y42) -> 202502.65 | AA42: =MIN(M42,I42-W42-Y42-Z42) -> 0 | AB42: =MIN(L42,I42-W42-Y42-Z42-AA42) -> 0 | AC42: =L42-AB42 -> 334968.95 | AD42: =N42-Z42 -> 2645796.9 | AE42: =M42-AA42 -> 38134224 | AF42: =O42-Y42 -> 0 | AG42: =F42+E42+H42+W42 -> 4448650.3 | AH42: =MIN(AC42,AG42) -> 334968.95 | AI42: =MIN(AE42,AG42-AH42) -> 4113681.3 | AJ42: =MIN(AD42,AG42-AH42-AI42) -> 0 | AK42: =MIN(AF42,AG42-AH42-AI42-AJ42) -> 0 | AL42: =AC42-AH42 -> 0 | AM42: =AE42-AI42 -> 34020543 | AN42: =AD42-AJ42 -> 2645796.9 | AO42: =AF42-AK42 -> 0 | AP42: =D42-E42-F42 -> 36666340 | AQ42: =SUM(AL42:AO42)-AP42 -> 0 | AR42: =SUMIFS(Python_Results!$C$2:$C$217,Python_Results!$A$2:$A$217,Assumptions!$B$10,Python_Results!$B$2:$B$217,A42) -> 36666340 | AS42: =SUMIFS(Python_Results!$D$2:$D$217,Python_Results!$A$2:$A$217,Assumptions!$B$10,Python_Results!$B$2:$B$217,A42) -> 0 | AT42: =SUMIFS(Python_Results!$E$2:$E$217,Python_Results!$A$2:$A$217,Assumptions!$B$10,Python_Results!$B$2:$B$217,A42) -> 34020543 | AU42: =SUMIFS(Python_Results!$F$2:$F$217,Python_Results!$A$2:$A$217,Assumptions!$B$10,Python_Results!$B$2:$B$217,A42) -> 2645796.9 | AV42: =SUMIFS(Python_Results!$G$2:$G$217,Python_Results!$A$2:$A$217,Assumptions!$B$10,Python_Results!$B$2:$B$217,A42) -> 0 | AW42: =AP42-AR42 -> -0.002228193 | AX42: =AL42-AS42 -> 0 | AY42: =AM42-AT42 -> -0.0041328445 | AZ42: =AN42-AU42 -> 0.0019046352 | BA42: =AO42-AV42 -> 0
A44: Logic: interest waterfall pays fees > Class A > B > C coupons; remaining excess spread first cures losses, the rest goes to equity. Uncovered losses write down Equity > C > B > A. Principal (scheduled + prepay + recoveries + excess used for losses) pays A > B > C > Equity sequentially.

Sheet PD_TermStructure
A1: DPD_Bucket | B1: HorizonMonths | C1: CumulativePD | D1: Key
A2: Current | B2: 1 | C2: 0 | D2: =A2&"|"&B2 -> Current|1
A3: 1-29 DPD | B3: 1 | C3: 0 | D3: =A3&"|"&B3 -> 1-29 DPD|1
A4: 30-59 DPD | B4: 1 | C4: 0 | D4: =A4&"|"&B4 -> 30-59 DPD|1
A5: 60-89 DPD | B5: 1 | C5: 0.369048 | D5: =A5&"|"&B5 -> 60-89 DPD|1
A6: Current | B6: 2 | C6: 0.001727 | D6: =A6&"|"&B6 -> Current|2
A7: 1-29 DPD | B7: 2 | C7: 0 | D7: =A7&"|"&B7 -> 1-29 DPD|2
A8: 30-59 DPD | B8: 2 | C8: 0.200161 | D8: =A8&"|"&B8 -> 30-59 DPD|2
A9: 60-89 DPD | B9: 2 | C9: 0.601899 | D9: =A9&"|"&B9 -> 60-89 DPD|2
A10: Current | B10: 3 | C10: 0.005833 | D10: =A10&"|"&B10 -> Current|3
A11: 1-29 DPD | B11: 3 | C11: 0.011175 | D11: =A11&"|"&B11 -> 1-29 DPD|3
A12: 30-59 DPD | B12: 3 | C12: 0.418053 | D12: =A12&"|"&B12 -> 30-59 DPD|3
A13: 60-89 DPD | B13: 3 | C13: 0.748817 | D13: =A13&"|"&B13 -> 60-89 DPD|3
... A241: 60-89 DPD | B241: 60 | C241: 1 | D241: =A241&"|"&B241 -> 60-89 DPD|60

Sheet ECL_LoanLevel
A1: Loan-level ECL cross-check (tape vs recomputed vs challenger)
A2: Blue = pasted from the tape / Python. Challenger columns L:Q are live formulas using PD_TermStructure and Assumptions!B3 (pool LGD).
A5: LoanID | B5: IFRS9 stage | C5: DPD status | D5: Remaining term | E5: Interest rate % | F5: PD (tape) | G5: LGD (tape) | H5: EAD | I5: ECL (tape) | J5: ECL recomputed | K5: Variance | L5: Horizon (m) | M5: Challenger PD | N5: Discount factor | O5: Challenger ECL | P5: Python challenger ECL | Q5: Diff vs Python
A6: ZAAUTO2024-1-00001 | B6: 1 | C6: Current | D6: 82 | E6: 8.11 | F6: 0.0224 | G6: 0.4521 | H6: 741356.86 | I6: 7507.75 | J6: =F6*G6*H6 -> 7507.7506 | K6: =J6-I6 -> 0.0005754944 | L6: =IF(B6=1,12,IF(B6=2,MIN(MAX(D6,1),60),6)) -> 12 | M6: =IF(B6=3,1,IFERROR(INDEX(PD_TermStructure!$C$2:$C$241,MATCH(C6&"|"&L6,PD_TermStructure!$D$2:$D$241,0)),0)) -> 0.109872 | N6: =(1+E6/100)^(-(L6/12)/2) -> 0.96176079 | O6: =IF(H6<=0,0,M6*Assumptions!$B$3*H6*N6) -> 32488.97 | P6: 32488.97 | Q6: =O6-P6 -> -0.00037588936
A7: ZAAUTO2024-1-00002 | B7: 1 | C7: 1-29 DPD | D7: 31 | E7: 11.36 | F7: 0.0224 | G7: 0.5551 | H7: 683790.85 | I7: 8502.42 | J7: =F7*G7*H7 -> 8502.4195 | K7: =J7-I7 -> -0.000461296 | L7: =IF(B7=1,12,IF(B7=2,MIN(MAX(D7,1),60),6)) -> 12 | M7: =IF(B7=3,1,IFERROR(INDEX(PD_TermStructure!$C$2:$C$241,MATCH(C7&"|"&L7,PD_TermStructure!$D$2:$D$241,0)),0)) -> 0.164153 | N7: =(1+E7/100)^(-(L7/12)/2) -> 0.94762255 | O7: =IF(H7<=0,0,M7*Assumptions!$B$3*H7*N7) -> 44112.536 | P7: 44112.54 | Q7: =O7-P7 -> -0.0036524489
A8: ZAAUTO2024-1-00003 | B8: 1 | C8: Current | D8: 58 | E8: 10.31 | F8: 0.0166 | G8: 0.6493 | H8: 300458.28 | I8: 3238.45 | J8: =F8*G8*H8 -> 3238.4535 | K8: =J8-I8 -> 0.0035159864 | L8: =IF(B8=1,12,IF(B8=2,MIN(MAX(D8,1),60),6)) -> 12 | M8: =IF(B8=3,1,IFERROR(INDEX(PD_TermStructure!$C$2:$C$241,MATCH(C8&"|"&L8,PD_TermStructure!$D$2:$D$241,0)),0)) -> 0.109872 | N8: =(1+E8/100)^(-(L8/12)/2) -> 0.95212191 | O8: =IF(H8<=0,0,M8*Assumptions!$B$3*H8*N8) -> 13035.218 | P8: 13035.22 | Q8: =O8-P8 -> -0.00209111
A9: ZAAUTO2024-1-00004 | B9: 1 | C9: Current | D9: 67 | E9: 13.53 | F9: 0.0241 | G9: 0.5023 | H9: 1024346.6 | I9: 12400.16 | J9: =F9*G9*H9 -> 12400.156 | K9: =J9-I9 -> -0.0040590163 | L9: =IF(B9=1,12,IF(B9=2,MIN(MAX(D9,1),60),6)) -> 12 | M9: =IF(B9=3,1,IFERROR(INDEX(PD_TermStructure!$C$2:$C$241,MATCH(C9&"|"&L9,PD_TermStructure!$D$2:$D$241,0)),0)) -> 0.109872 | N9: =(1+E9/100)^(-(L9/12)/2) -> 0.93852248 | O9: =IF(H9<=0,0,M9*Assumptions!$B$3*H9*N9) -> 43805.957 | P9: 43805.96 | Q9: =O9-P9 -> -0.0034280321
A10: ZAAUTO2024-1-00005 | B10: 1 | C10: Current | D10: 0 | E10: 12.62 | F10: 0.0193 | G10: 0.5053 | H10: 0 | I10: 0 | J10: =F10*G10*H10 -> 0 | K10: =J10-I10 -> 0 | L10: =IF(B10=1,12,IF(B10=2,MIN(MAX(D10,1),60),6)) -> 12 | M10: =IF(B10=3,1,IFERROR(INDEX(PD_TermStructure!$C$2:$C$241,MATCH(C10&"|"&L10,PD_TermStructure!$D$2:$D$241,0)),0)) -> 0.109872 | N10: =(1+E10/100)^(-(L10/12)/2) -> 0.94230661 | O10: =IF(H10<=0,0,M10*Assumptions!$B$3*H10*N10) -> 0 | P10: 0 | Q10: =O10-P10 -> 0
A11: ZAAUTO2024-1-00006 | B11: 1 | C11: Current | D11: 81 | E11: 8.43 | F11: 0.0147 | G11: 0.5685 | H11: 490997.99 | I11: 4103.25 | J11: =F11*G11*H11 -> 4103.2457 | K11: =J11-I11 -> -0.0043474695 | L11: =IF(B11=1,12,IF(B11=2,MIN(MAX(D11,1),60),6)) -> 12 | M11: =IF(B11=3,1,IFERROR(INDEX(PD_TermStructure!$C$2:$C$241,MATCH(C11&"|"&L11,PD_TermStructure!$D$2:$D$241,0)),0)) -> 0.109872 | N11: =(1+E11/100)^(-(L11/12)/2) -> 0.96034056 | O11: =IF(H11<=0,0,M11*Assumptions!$B$3*H11*N11) -> 21485.554 | P11: 21485.55 | Q11: =O11-P11 -> 0.0035148587
A12: ZAAUTO2024-1-00007 | B12: 1 | C12: Current | D12: 70 | E12: 13.35 | F12: 0.0159 | G12: 0.439 | H12: 611192.31 | I12: 4266.18 | J12: =F12*G12*H12 -> 4266.1834 | K12: =J12-I12 -> 0.003443031 | L12: =IF(B12=1,12,IF(B12=2,MIN(MAX(D12,1),60),6)) -> 12 | M12: =IF(B12=3,1,IFERROR(INDEX(PD_TermStructure!$C$2:$C$241,MATCH(C12&"|"&L12,PD_TermStructure!$D$2:$D$241,0)),0)) -> 0.109872 | N12: =(1+E12/100)^(-(L12/12)/2) -> 0.93926738 | O12: =IF(H12<=0,0,M12*Assumptions!$B$3*H12*N12) -> 26158.25 | P12: 26158.25 | Q12: =O12-P12 -> -0.00035178124
A13: ZAAUTO2024-1-00008 | B13: 2 | C13: 60-89 DPD | D13: 60 | E13: 8.34 | F13: 0.117 | G13: 0.6495 | H13: 315288.3 | I13: 23959.23 | J13: =F13*G13*H13 -> 23959.231 | K13: =J13-I13 -> 0.00084945 | L13: =IF(B13=1,12,IF(B13=2,MIN(MAX(D13,1),60),6)) -> 60 | M13: =IF(B13=3,1,IFERROR(INDEX(PD_TermStructure!$C$2:$C$241,MATCH(C13&"|"&L13,PD_TermStructure!$D$2:$D$241,0)),0)) -> 1 | N13: =(1+E13/100)^(-(L13/12)/2) -> 0.81851741 | O13: =IF(H13<=0,0,M13*Assumptions!$B$3*H13*N13) -> 107026.25 | P13: 107026.25 | Q13: =O13-P13 -> -0.00023940322
A14: ZAAUTO2024-1-00009 | B14: 1 | C14: Current | D14: 55 | E14: 7.55 | F14: 0.0216 | G14: 0.5988 | H14: 805215.48 | I14: 10414.72 | J14: =F14*G14*H14 -> 10414.721 | K14: =J14-I14 -> 0.0014355584 | L14: =IF(B14=1,12,IF(B14=2,MIN(MAX(D14,1),60),6)) -> 12 | M14: =IF(B14=3,1,IFERROR(INDEX(PD_TermStructure!$C$2:$C$241,MATCH(C14&"|"&L14,PD_TermStructure!$D$2:$D$241,0)),0)) -> 0.109872 | N14: =(1+E14/100)^(-(L14/12)/2) -> 0.96426142 | O14: =IF(H14<=0,0,M14*Assumptions!$B$3*H14*N14) -> 35379.238 | P14: 35379.24 | Q14: =O14-P14 -> -0.0024513692
A15: ZAAUTO2024-1-00010 | B15: 3 | C15: 120+ DPD | D15: 31 | E15: 7.79 | F15: 1 | G15: 0.6092 | H15: 230067.02 | I15: 140156.83 | J15: =F15*G15*H15 -> 140156.83 | K15: =J15-I15 -> -0.001416 | L15: =IF(B15=1,12,IF(B15=2,MIN(MAX(D15,1),60),6)) -> 6 | M15: =IF(B15=3,1,IFERROR(INDEX(PD_TermStructure!$C$2:$C$241,MATCH(C15&"|"&L15,PD_TermStructure!$D$2:$D$241,0)),0)) -> 1 | N15: =(1+E15/100)^(-(L15/12)/2) -> 0.98142108 | O15: =IF(H15<=0,0,M15*Assumptions!$B$3*H15*N15) -> 93640.62 | P15: 93640.62 | Q15: =O15-P15 -> -3.5072153e-05
A16: ZAAUTO2024-1-00011 | B16: 2 | C16: 30-59 DPD | D16: 42 | E16: 9.8 | F16: 0.1117 | G16: 0.523 | H16: 461015.87 | I16: 26932.13 | J16: =F16*G16*H16 -> 26932.132 | K16: =J16-I16 -> 0.002211117 | L16: =IF(B16=1,12,IF(B16=2,MIN(MAX(D16,1),60),6)) -> 42 | M16: =IF(B16=3,1,IFERROR(INDEX(PD_TermStructure!$C$2:$C$241,MATCH(C16&"|"&L16,PD_TermStructure!$D$2:$D$241,0)),0)) -> 1 | N16: =(1+E16/100)^(-(L16/12)/2) -> 0.84907471 | O16: =IF(H16<=0,0,M16*Assumptions!$B$3*H16*N16) -> 162336.55 | P16: 162336.55 | Q16: =O16-P16 -> -0.00012189982
A17: ZAAUTO2024-1-00012 | B17: 1 | C17: Current | D17: 19 | E17: 12.17 | F17: 0.0196 | G17: 0.4826 | H17: 206002.75 | I17: 1948.57 | J17: =F17*G17*H17 -> 1948.5718 | K17: =J17-I17 -> 0.00177214 | L17: =IF(B17=1,12,IF(B17=2,MIN(MAX(D17,1),60),6)) -> 12 | M17: =IF(B17=3,1,IFERROR(INDEX(PD_TermStructure!$C$2:$C$241,MATCH(C17&"|"&L17,PD_TermStructure!$D$2:$D$241,0)),0)) -> 0.109872 | N17: =(1+E17/100)^(-(L17/12)/2) -> 0.94419488 | O17: =IF(H17<=0,0,M17*Assumptions!$B$3*H17*N17) -> 8862.9076 | P17: 8862.91 | Q17: =O17-P17 -> -0.0024493042
... A505: ZAAUTO2024-1-00500 | B505: 1 | C505: 1-29 DPD | D505: 70 | E505: 12.3 | F505: 0.0172 | G505: 0.6181 | H505: 1457447 | I505: 15494.59 | J505: =F505*G505*H505 -> 15494.586 | K505: =J505-I505 -> -0.0042410204 | L505: =IF(B505=1,12,IF(B505=2,MIN(MAX(D505,1),60),6)) -> 12 | M505: =IF(B505=3,1,IFERROR(INDEX(PD_TermStructure!$C$2:$C$241,MATCH(C505&"|"&L505,PD_TermStructure!$D$2:$D$241,0)),0)) -> 0.164153 | N505: =(1+E505/100)^(-(L505/12)/2) -> 0.94364821 | O505: =IF(H505<=0,0,M505*Assumptions!$B$3*H505*N505) -> 93628.11 | P505: 93628.11 | Q505: =O505-P505 -> -1.1577213e-06
