Workbook

Sheet Measure Dictionary
A1: ID | B1: Day | C1: Category | D1: Measure | E1: DAX formula | F1: Business purpose | G1: Depends on | H1: Format | I1: Expected value (Python check) | J1: Value in Power BI | K1: Matches? (formula) | L1: DAX Studio ms | M1: Tested (Y/N)
A2: D03-01 | B2: 3 | C2: Pool | D2: Total Outstanding Balance | E2: SUM ( FactLoanTape[CurrentBalance] ) | F2: Current principal outstanding on the pool. | H2: #,##0 | I2: 3.177852e+08 | K2: =IF(OR(J2="",I2=""),"",IF(ABS(J2-I2)<=MAX(0.0001,ABS(I2)*0.0001),"MATCH","CHECK"))
A3: D03-02 | B3: 3 | C3: Pool | D3: Original Balance | E3: SUM ( DimLoan[OriginalLoanAmount] ) | F3: Original principal advanced at origination. | H3: #,##0 | I3: 546073700 | K3: =IF(OR(J3="",I3=""),"",IF(ABS(J3-I3)<=MAX(0.0001,ABS(I3)*0.0001),"MATCH","CHECK"))
A4: D03-03 | B4: 3 | C4: Pool | D4: Pool Factor | E4: DIVIDE ( [Total Outstanding Balance], [Original Balance] ) | F4: Share of original balance still outstanding. | G4: Original Balance, Total Outstanding Balance | H4: 0.0% | I4: 0.581946 | K4: =IF(OR(J4="",I4=""),"",IF(ABS(J4-I4)<=MAX(0.0001,ABS(I4)*0.0001),"MATCH","CHECK"))
A5: D03-04 | B5: 3 | C5: Pool | D5: Total EAD | E5: SUM ( FactLoanTape[EAD] ) | F5: Exposure at default used for ECL. | H5: #,##0 | I5: 3.2616417e+08 | K5: =IF(OR(J5="",I5=""),"",IF(ABS(J5-I5)<=MAX(0.0001,ABS(I5)*0.0001),"MATCH","CHECK"))
A6: D03-05 | B6: 3 | C6: Counts | D6: Loan Count | E6: COUNTROWS ( FactLoanTape ) | F6: All loans on the tape. | H6: #,##0 | I6: 500 | K6: =IF(OR(J6="",I6=""),"",IF(ABS(J6-I6)<=MAX(0.0001,ABS(I6)*0.0001),"MATCH","CHECK"))
A7: D03-06 | B7: 3 | C7: Counts | D7: Active Loans | E7: CALCULATE ( COUNTROWS ( FactLoanTape ), FactLoanTape[CurrentBalance] > 0 ) | F7: Loans with a positive balance (24 loans carry zero balance). | H7: #,##0 | I7: 476 | K7: =IF(OR(J7="",I7=""),"",IF(ABS(J7-I7)<=MAX(0.0001,ABS(I7)*0.0001),"MATCH","CHECK"))
A8: D03-07 | B8: 3 | C8: Counts | D8: Defaulted Loans | E8: CALCULATE ( COUNTROWS ( FactLoanTape ), FactLoanTape[IsDefaulted] = 1 ) | F8: Loans flagged Default or Repossessed. | H8: #,##0 | I8: 9 | K8: =IF(OR(J8="",I8=""),"",IF(ABS(J8-I8)<=MAX(0.0001,ABS(I8)*0.0001),"MATCH","CHECK"))
A9: D03-08 | B9: 3 | C9: Counts | D9: Prepaid Loans | E9: CALCULATE ( COUNTROWS ( FactLoanTape ), FactLoanTape[PrepaymentAmount] > 0 ) | F9: Loans with a voluntary prepayment. | H9: #,##0
A10: D03-09 | B10: 3 | C10: Balances | D10: Defaulted Balance | E10: CALCULATE ( [Total Outstanding Balance], FactLoanTape[IsDefaulted] = 1 ) | F10: Outstanding balance of defaulted loans. | G10: Total Outstanding Balance | H10: #,##0
A11: D03-10 | B11: 3 | C11: Delinquency | D11: Balance Current | E11: CALCULATE ( [Total Outstanding Balance], FactLoanTape[DelinquencyStatus] = "Current" ) | F11: Balance with no arrears. | G11: Total Outstanding Balance | H11: #,##0
A12: D03-11 | B12: 3 | C12: Delinquency | D12: Balance 1-29 DPD | E12: CALCULATE ( [Total Outstanding Balance], FactLoanTape[DelinquencyStatus] = "1-29 DPD" ) | F12: Balance 1-29 days past due. | G12: Total Outstanding Balance | H12: #,##0
A13: D03-12 | B13: 3 | C13: Delinquency | D13: Balance 30 DPD | E13: CALCULATE ( [Total Outstanding Balance], FactLoanTape[DelinquencyStatus] = "30-59 DPD" ) | F13: Balance 30-59 days past due. | G13: Total Outstanding Balance | H13: #,##0
A14: D03-13 | B14: 3 | C14: Delinquency | D14: Balance 60 DPD | E14: CALCULATE ( [Total Outstanding Balance], FactLoanTape[DelinquencyStatus] = "60-89 DPD" ) | F14: Balance 60-89 days past due. | G14: Total Outstanding Balance | H14: #,##0
A15: D03-14 | B15: 3 | C15: Delinquency | D15: Balance 90 DPD | E15: CALCULATE ( [Total Outstanding Balance], FactLoanTape[DelinquencyStatus] = "90-119 DPD" ) | F15: Balance 90-119 days past due. | G15: Total Outstanding Balance | H15: #,##0
A16: D03-15 | B16: 3 | C16: Delinquency | D16: Balance 120+ DPD | E16: CALCULATE ( [Total Outstanding Balance], FactLoanTape[DelinquencyStatus] IN { "120+ DPD", "Default", "Repossessed" } ) | F16: Balance 120+ DPD plus Default/Repossessed. | G16: Total Outstanding Balance | H16: #,##0
A17: D03-16 | B17: 3 | C17: Delinquency | D17: Delinquent 30+ Balance | E17: CALCULATE ( [Total Outstanding Balance], FactLoanTape[DelinquencyDays] >= 30 ) | F17: Balance 30 or more days past due. | G17: Total Outstanding Balance | H17: #,##0
A18: D03-17 | B18: 3 | C18: Delinquency | D18: Delinquent 30+ % | E18: DIVIDE ( [Delinquent 30+ Balance], [Total Outstanding Balance] ) | F18: 30+ DPD as % of pool balance (SMA-1 and worse). | G18: Delinquent 30+ Balance, Total Outstanding Balance | H18: 0.0% | I18: 0.141141 | K18: =IF(OR(J18="",I18=""),"",IF(ABS(J18-I18)<=MAX(0.0001,ABS(I18)*0.0001),"MATCH","CHECK"))
A19: D03-18 | B19: 3 | C19: Delinquency | D19: Delinquent 60+ Balance | E19: CALCULATE ( [Total Outstanding Balance], FactLoanTape[DelinquencyDays] >= 60 ) | F19: Balance 60 or more days past due. | G19: Total Outstanding Balance | H19: #,##0
A20: D03-19 | B20: 3 | C20: Delinquency | D20: Delinquent 60+ % | E20: DIVIDE ( [Delinquent 60+ Balance], [Total Outstanding Balance] ) | F20: 60+ DPD as % of pool; drives the delinquency trigger. | G20: Delinquent 60+ Balance, Total Outstanding Balance | H20: 0.0% | I20: 0.105873 | K20: =IF(OR(J20="",I20=""),"",IF(ABS(J20-I20)<=MAX(0.0001,ABS(I20)*0.0001),"MATCH","CHECK"))
A21: D03-20 | B21: 3 | C21: Delinquency | D21: Delinquent 90+ Balance | E21: CALCULATE ( [Total Outstanding Balance], FactLoanTape[DelinquencyDays] >= 90 ) | F21: Balance 90 or more days past due (NPA). | G21: Total Outstanding Balance | H21: #,##0
A22: D03-21 | B22: 3 | C22: Delinquency | D22: Delinquent 90+ % | E22: DIVIDE ( [Delinquent 90+ Balance], [Total Outstanding Balance] ) | F22: NPA ratio. | G22: Delinquent 90+ Balance, Total Outstanding Balance | H22: 0.0% | I22: 0.055695 | K22: =IF(OR(J22="",I22=""),"",IF(ABS(J22-I22)<=MAX(0.0001,ABS(I22)*0.0001),"MATCH","CHECK"))
A23: D03-22 | B23: 3 | C23: Weighted avg | D23: WAC | E23: DIVIDE ( SUMX ( FactLoanTape, RELATED ( DimLoan[InterestRate] ) * FactLoanTape[CurrentBalance] ), [Total Outstanding Balance] ) / 100 | F23: Weighted-average coupon (rate in tape is in % points). | G23: Total Outstanding Balance | H23: 0.00% | I23: 0.109455 | K23: =IF(OR(J23="",I23=""),"",IF(ABS(J23-I23)<=MAX(0.0001,ABS(I23)*0.0001),"MATCH","CHECK"))
A24: D03-23 | B24: 3 | C24: Weighted avg | D24: WAM | E24: DIVIDE ( SUMX ( FactLoanTape, FactLoanTape[RemainingTerm] * FactLoanTape[CurrentBalance] ), [Total Outstanding Balance] ) | F24: Weighted-average remaining maturity (months). | G24: Total Outstanding Balance | H24: 0.0 | I24: 45.142781 | K24: =IF(OR(J24="",I24=""),"",IF(ABS(J24-I24)<=MAX(0.0001,ABS(I24)*0.0001),"MATCH","CHECK"))
A25: D03-24 | B25: 3 | C25: Weighted avg | D25: WALA | E25: DIVIDE ( SUMX ( FactLoanTape, FactLoanTape[MonthsOnBook] * FactLoanTape[CurrentBalance] ), [Total Outstanding Balance] ) | F25: Weighted-average loan age (months on book). | G25: Total Outstanding Balance | H25: 0.0 | I25: 16.755706 | K25: =IF(OR(J25="",I25=""),"",IF(ABS(J25-I25)<=MAX(0.0001,ABS(I25)*0.0001),"MATCH","CHECK"))
A26: D03-25 | B26: 3 | C26: Weighted avg | D26: WALT | E26: DIVIDE ( SUMX ( FactLoanTape, RELATED ( DimLoan[OriginalTerm] ) * FactLoanTape[CurrentBalance] ), [Total Outstanding Balance] ) | F26: Weighted-average original loan term (months). | G26: Total Outstanding Balance | H26: 0.0 | I26: 61.898488 | K26: =IF(OR(J26="",I26=""),"",IF(ABS(J26-I26)<=MAX(0.0001,ABS(I26)*0.0001),"MATCH","CHECK"))
A27: D03-26 | B27: 3 | C27: Weighted avg | D27: WA LTV Origination | E27: DIVIDE ( SUMX ( FactLoanTape, FactLoanTape[LTV_AtOrigination] * FactLoanTape[CurrentBalance] ), [Total Outstanding Balance] ) | F27: Balance-weighted LTV at origination. | G27: Total Outstanding Balance | H27: 0.0%
A28: D03-27 | B28: 3 | C28: Weighted avg | D28: WA LTV Current | E28: DIVIDE ( SUMX ( FactLoanTape, FactLoanTape[LTV_Current] * FactLoanTape[CurrentBalance] ), [Total Outstanding Balance] ) | F28: Balance-weighted current LTV. | G28: Total Outstanding Balance | H28: 0.0% | I28: 0.675413 | K28: =IF(OR(J28="",I28=""),"",IF(ABS(J28-I28)<=MAX(0.0001,ABS(I28)*0.0001),"MATCH","CHECK"))
A29: D03-28 | B29: 3 | C29: Weighted avg | D29: WA CIBIL | E29: DIVIDE ( SUMX ( FactLoanTape, FactLoanTape[CIBIL_Score_Current] * FactLoanTape[CurrentBalance] ), [Total Outstanding Balance] ) | F29: Balance-weighted current CIBIL score. | G29: Total Outstanding Balance | H29: 0 | I29: 742.43926 | K29: =IF(OR(J29="",I29=""),"",IF(ABS(J29-I29)<=MAX(0.0001,ABS(I29)*0.0001),"MATCH","CHECK"))
A30: D03-29 | B30: 3 | C30: Weighted avg | D30: WA CIBIL Origination | E30: DIVIDE ( SUMX ( FactLoanTape, FactLoanTape[CIBIL_Score_Origination] * FactLoanTape[CurrentBalance] ), [Total Outstanding Balance] ) | F30: Balance-weighted CIBIL at origination. | G30: Total Outstanding Balance | H30: 0
A31: D03-30 | B31: 3 | C31: Weighted avg | D31: WA DTI | E31: DIVIDE ( SUMX ( FactLoanTape, FactLoanTape[DTI_Ratio] * FactLoanTape[CurrentBalance] ), [Total Outstanding Balance] ) | F31: Balance-weighted debt-to-income. | G31: Total Outstanding Balance | H31: 0.0% | I31: 0.239732 | K31: =IF(OR(J31="",I31=""),"",IF(ABS(J31-I31)<=MAX(0.0001,ABS(I31)*0.0001),"MATCH","CHECK"))
A32: D03-31 | B32: 3 | C32: Pool | D32: Average Loan Balance | E32: DIVIDE ( [Total Outstanding Balance], [Active Loans] ) | F32: Mean balance of active loans. | G32: Active Loans, Total Outstanding Balance | H32: #,##0
A33: D03-32 | B33: 3 | C33: Pool | D33: Largest Loan Balance | E33: MAX ( FactLoanTape[CurrentBalance] ) | F33: Single largest exposure. | H33: #,##0
A34: D03-33 | B34: 3 | C34: Pool | D34: Insured Loan % | E34: DIVIDE ( CALCULATE ( [Total Outstanding Balance], DimLoan[HasInsurance] = 1 ), [Total Outstanding Balance] ) | F34: Balance share with any vehicle insurance. | G34: Total Outstanding Balance | H34: 0.0%
A35: D03-34 | B35: 3 | C35: Pool | D35: New Vehicle % | E35: DIVIDE ( CALCULATE ( [Total Outstanding Balance], DimVehicle[IsNewVehicle] = 1 ), [Total Outstanding Balance] ) | F35: Balance share financing new vehicles. | G35: Total Outstanding Balance | H35: 0.0%
A36: D03-35 | B36: 3 | C36: Pool | D36: Modified Loan % | E36: DIVIDE ( CALCULATE ( COUNTROWS ( FactLoanTape ), DimLoan[IsModified] = 1 ), [Loan Count] ) | F36: Share of loans restructured (deferral, extension, rate cut). | G36: Loan Count | H36: 0.0%
A37: D03-36 | B37: 3 | C37: Loss | D37: Total Prepayments | E37: SUM ( FactLoanTape[PrepaymentAmount] ) | F37: Voluntary prepayments recorded on the tape. | H37: #,##0
A38: D03-37 | B38: 3 | C38: Loss | D38: Total Loss Amount | E38: SUM ( FactLoanTape[LossAmount] ) | F38: Gross realised loss on the tape. | H38: #,##0
A39: D03-38 | B39: 3 | C39: Loss | D39: Total Recoveries | E39: SUM ( FactLoanTape[RecoveryAmount] ) | F39: Recoveries on the tape. | H39: #,##0
A40: D03-39 | B40: 3 | C40: Loss | D40: Total Net Loss (Tape) | E40: SUM ( FactLoanTape[NetLoss] ) | F40: Net realised loss on the tape. | H40: #,##0
A41: D03-40 | B41: 3 | C41: Collections | D41: Payment Collection Rate | E41: DIVIDE ( SUM ( FactLoanTape[LastPaymentAmount] ), SUM ( FactLoanTape[ScheduledPaymentDue] ) ) | F41: Last payment received vs scheduled payment due. | H41: 0.0%
A42: D04-01 | B42: 4 | C42: Base | D42: Net Loss (Monthly) | E42: CALCULATE ( SUM ( FactDynamicLoss[NetLoss_ThisMonth] ), FactDynamicLoss[IncludeInTrend] = 1 ) | F42: Monthly net loss (second 30-May row excluded - see Data Quality DQ08). | H42: #,##0
A43: D04-02 | B43: 4 | C43: Base | D43: Gross Loss (Monthly) | E43: CALCULATE ( SUM ( FactDynamicLoss[GrossLoss_ThisMonth] ), FactDynamicLoss[IncludeInTrend] = 1 ) | F43: Monthly gross loss. | H43: #,##0
A44: D04-03 | B44: 4 | C44: Base | D44: Recoveries (Monthly) | E44: CALCULATE ( SUM ( FactDynamicLoss[Recoveries_ThisMonth] ), FactDynamicLoss[IncludeInTrend] = 1 ) | F44: Monthly recoveries. | H44: #,##0
A45: D04-04 | B45: 4 | C45: Base | D45: New Defaults Balance (Monthly) | E45: CALCULATE ( SUM ( FactDynamicLoss[NewDefaults_Balance] ), FactDynamicLoss[IncludeInTrend] = 1 ) | F45: Balance newly defaulted in the month. | H45: #,##0
A46: D04-05 | B46: 4 | C46: Base | D46: BOP Balance (Monthly) | E46: CALCULATE ( SUM ( FactDynamicLoss[BOP_Balance] ), FactDynamicLoss[IncludeInTrend] = 1 ) | F46: Beginning-of-period pool balance. | H46: #,##0
A47: D04-06 | B47: 4 | C47: Base | D47: Monthly Default Rate | E47: DIVIDE ( [New Defaults Balance (Monthly)], [BOP Balance (Monthly)] ) | F47: New defaults / opening balance. | G47: BOP Balance (Monthly), New Defaults Balance (Monthly) | H47: 0.000%
A48: D04-07 | B48: 4 | C48: Base | D48: Monthly Net Loss Rate | E48: DIVIDE ( [Net Loss (Monthly)], [BOP Balance (Monthly)] ) | F48: Net loss / opening balance. | G48: BOP Balance (Monthly), Net Loss (Monthly) | H48: 0.000%
A49: D04-08 | B49: 4 | C49: To-date | D49: Net Loss MTD | E49: TOTALMTD ( [Net Loss (Monthly)], DimDate[Date] ) | F49: Month-to-date net loss. | G49: Net Loss (Monthly) | H49: #,##0
A50: D04-09 | B50: 4 | C50: To-date | D50: Net Loss QTD | E50: TOTALQTD ( [Net Loss (Monthly)], DimDate[Date] ) | F50: Quarter-to-date net loss. | G50: Net Loss (Monthly) | H50: #,##0
A51: D04-10 | B51: 4 | C51: To-date | D51: Net Loss YTD | E51: TOTALYTD ( [Net Loss (Monthly)], DimDate[Date] ) | F51: Calendar year-to-date net loss. | G51: Net Loss (Monthly) | H51: #,##0
A52: D04-11 | B52: 4 | C52: To-date | D52: Net Loss FYTD | E52: VAR fy = MAX ( DimDate[FiscalYear] ) VAR d = MAX ( DimDate[Date] ) RETURN CALCULATE ( [Net Loss (Monthly)], FILTER ( ALL ( DimDate ), DimDate[FiscalYear] = fy && DimDate[Date] <= d ) ) | F52: Indian fiscal year-to-date (April-March) net loss; built on DimDate[FiscalYear] so it does not depend on locale date strings. | G52: Net Loss (Monthly) | H52: #,##0
A53: D04-12 | B53: 4 | C53: Comparison | D53: Net Loss Prior Month | E53: CALCULATE ( [Net Loss (Monthly)], DATEADD ( DimDate[Date], -1, MONTH ) ) | F53: Net loss one month earlier. | G53: Net Loss (Monthly) | H53: #,##0
A54: D04-13 | B54: 4 | C54: Comparison | D54: Net Loss MoM % | E54: DIVIDE ( [Net Loss (Monthly)] - [Net Loss Prior Month], [Net Loss Prior Month] ) | F54: Month-on-month change in net loss. | G54: Net Loss (Monthly), Net Loss Prior Month | H54: 0.0%
A55: D04-14 | B55: 4 | C55: Comparison | D55: Default Rate Prior Quarter | E55: CALCULATE ( [Monthly Default Rate], DATEADD ( DimDate[Date], -1, QUARTER ) ) | F55: Monthly default rate one quarter earlier. | G55: Monthly Default Rate | H55: 0.000%
A56: D04-15 | B56: 4 | C56: Comparison | D56: Default Rate QoQ Change | E56: [Monthly Default Rate] - [Default Rate Prior Quarter] | F56: Quarter-on-quarter change (pts). | G56: Default Rate Prior Quarter, Monthly Default Rate | H56: 0.000%
A57: D04-16 | B57: 4 | C57: Comparison | D57: Default Rate vs Prior Year | E57: CALCULATE ( [Monthly Default Rate], SAMEPERIODLASTYEAR ( DimDate[Date] ) ) | F57: Prior-year comparator (blank: file covers < 12 months). | G57: Monthly Default Rate | H57: 0.000%
A58: D04-17 | B58: 4 | C58: Rolling | D58: Rolling 3M Default Rate | E58: VAR LastD = MAX ( FactDynamicLoss[MonthEnd] ) VAR Win = DATESINPERIOD ( DimDate[Date], LastD, -3, MONTH ) RETURN DIVIDE ( CALCULATE ( [New Defaults Balance (Monthly)], Win ), CALCULATE ( [BOP Balance (Monthly)], Win ) ) | F58: Balance-weighted default rate over the trailing 3 months. | G58: BOP Balance (Monthly), New Defaults Balance (Monthly) | H58: 0.000%
... A63: D04-22 | B63: 4 | C63: Alerts | D63: Default Rate Z-Score | E63: DIVIDE ( [Monthly Default Rate] - [Default Rate 12M Average], [Default Rate 12M StdDev] ) | F63: Standard deviations from the 12-month average. | G63: Default Rate 12M Average, Default Rate 12M StdDev, Monthly Default Rate | H63: 0.00
A64: D04-23 | B64: 4 | C64: Alerts | D64: Default Rate Trend Alert | E64: IF ( ABS ( [Default Rate Z-Score] ) > 2, "ALERT: > 2 std dev", "Within range" ) | F64: Flags metrics moving more than 2 std dev from their 12M average (brief Day 4). | G64: Default Rate Z-Score
A65: D04-24 | B65: 4 | C65: Alerts | D65: Delinquency 30+ Z-Score | E65: VAR LastD = MAX ( FactDynamicLoss[MonthEnd] ) VAR Months12 = CALCULATETABLE ( VALUES ( DimDate[Date] ), DATESINPERIOD ( DimDate[Date], LastD, -12, MONTH ), DimDate[IsMonthEnd] = 1 ) VAR Cur = [DPD 30+ % (Date View)] RETURN DIVIDE ( Cur - AVERAGEX ( Months12, [DPD 30+ % (Date View)] ), STDEVX.P ( Months12, [DPD 30+ % (Date View)] ) ) | F65: Z-score of 30+ DPD share vs its 12M history. | G65: DPD 30+ % (Date View) | H65: 0.00
A66: D05-01 | B66: 5 | C66: Strat | D66: Pool Share % | E66: DIVIDE ( [Total Outstanding Balance], CALCULATE ( [Total Outstanding Balance], ALLSELECTED () ) ) | F66: Share of the selected pool - use with any stratification axis (LTV band, CIBIL band, vintage). | G66: Total Outstanding Balance | H66: 0.0%
A67: D05-02 | B67: 5 | C67: Strat | D67: LTV > 90% Share | E67: DIVIDE ( CALCULATE ( [Total Outstanding Balance], FactLoanTape[LTV_Current] > 0.9 ), [Total Outstanding Balance] ) | F67: Balance share with current LTV above 90%. | G67: Total Outstanding Balance | H67: 0.0%
A68: D05-03 | B68: 5 | C68: Strat | D68: CIBIL < 650 Share | E68: DIVIDE ( CALCULATE ( [Total Outstanding Balance], FactLoanTape[CIBIL_Score_Current] < 650 ), [Total Outstanding Balance] ) | F68: Balance share with sub-650 CIBIL. | G68: Total Outstanding Balance | H68: 0.0%
A69: D05-04 | B69: 5 | C69: Concentration | D69: Top 3 States | E69: CONCATENATEX ( TOPN ( 3, VALUES ( DimGeography[State] ), [Total Outstanding Balance], DESC ), DimGeography[State] & " " & FORMAT ( DIVIDE ( [Total Outstanding Balance], CALCULATE ( [Total Outstanding Balance], ALLSELECTED ( DimGeography ) ) ), "0.0%" ), ", ", [Total Outstanding Balance], DESC ) | F69: Text label of the three largest states with their share. | G69: Total Outstanding Balance
A70: D05-05 | B70: 5 | C70: Concentration | D70: Top 5 State Concentration | E70: DIVIDE ( SUMX ( TOPN ( 5, VALUES ( DimGeography[State] ), [Total Outstanding Balance], DESC ), [Total Outstanding Balance] ), [Total Outstanding Balance] ) | F70: Share of the pool in the five largest states (TOPN virtual table). | G70: Total Outstanding Balance | H70: 0.0% | I70: 0.376958 | K70: =IF(OR(J70="",I70=""),"",IF(ABS(J70-I70)<=MAX(0.0001,ABS(I70)*0.0001),"MATCH","CHECK"))
A71: D05-06 | B71: 5 | C71: Concentration | D71: Top 10 Loan Concentration | E71: DIVIDE ( SUMX ( TOPN ( 10, VALUES ( DimLoan[LoanID] ), [Total Outstanding Balance], DESC ), [Total Outstanding Balance] ), [Total Outstanding Balance] ) | F71: Share held by the ten largest loans. | G71: Total Outstanding Balance | H71: 0.0%
A72: D05-07 | B72: 5 | C72: Concentration | D72: Top 10 Borrower Concentration | E72: DIVIDE ( SUMX ( TOPN ( 10, VALUES ( DimBorrower[BorrowerID] ), [Total Outstanding Balance], DESC ), [Total Outstanding Balance] ), [Total Outstanding Balance] ) | F72: Share held by the ten largest borrowers. | G72: Total Outstanding Balance | H72: 0.0%
A73: D05-08 | B73: 5 | C73: Concentration | D73: HHI State | E73: VAR Tot = [Total Outstanding Balance] RETURN SUMX ( VALUES ( DimGeography[State] ), POWER ( DIVIDE ( [Total Outstanding Balance], Tot ), 2 ) ) | F73: Herfindahl-Hirschman Index by state (0-1). | G73: Total Outstanding Balance | H73: 0.0000 | I73: 0.058122 | K73: =IF(OR(J73="",I73=""),"",IF(ABS(J73-I73)<=MAX(0.0001,ABS(I73)*0.0001),"MATCH","CHECK"))
A74: D05-09 | B74: 5 | C74: Concentration | D74: HHI Servicer | E74: VAR Tot = [Total Outstanding Balance] RETURN SUMX ( VALUES ( DimLoan[ServicerName] ), POWER ( DIVIDE ( [Total Outstanding Balance], Tot ), 2 ) ) | F74: HHI by servicer. | G74: Total Outstanding Balance | H74: 0.0000
A75: D05-10 | B75: 5 | C75: Concentration | D75: HHI Vehicle Make | E75: VAR Tot = [Total Outstanding Balance] RETURN SUMX ( VALUES ( DimVehicle[VehicleMake] ), POWER ( DIVIDE ( [Total Outstanding Balance], Tot ), 2 ) ) | F75: HHI by vehicle manufacturer. | G75: Total Outstanding Balance | H75: 0.0000
A76: D05-11 | B76: 5 | C76: Concentration | D76: HHI Borrower | E76: VAR Tot = [Total Outstanding Balance] RETURN SUMX ( VALUES ( DimBorrower[BorrowerID] ), POWER ( DIVIDE ( [Total Outstanding Balance], Tot ), 2 ) ) | F76: HHI by borrower (borrower IDs are unique in this tape). | G76: Total Outstanding Balance | H76: 0.0000
A77: D05-12 | B77: 5 | C77: Ranking | D77: State Rank | E77: RANKX ( ALLSELECTED ( DimGeography[State] ), [Total Outstanding Balance], , DESC, DENSE ) | F77: Rank of each state by balance. | G77: Total Outstanding Balance | H77: 0
A78: D05-13 | B78: 5 | C78: Ranking | D78: Distinct States | E78: DISTINCTCOUNT ( DimLoan[State] ) | F78: Number of states in the selection. | H78: 0
A79: D05-14 | B79: 5 | C79: Context transition | D79: Portfolio ECL (Context Transition) | E79: SUMX ( FactLoanTape, CALCULATE ( AVERAGE ( FactLoanTape[PD_Estimate] ) * AVERAGE ( FactLoanTape[LGD_Estimate] ) ) * FactLoanTape[EAD] ) | F79: Context-transition demonstration: CALCULATE inside SUMX turns each row into a filter context (brief Day 5). | H79: #,##0
A80: D06-01 | B80: 6 | C80: Pool cash flow | D80: Ending Pool Balance | E80: VAR p = MAX ( FactPool[period] ) RETURN CALCULATE ( SUM ( FactPool[ending_pool] ), FactPool[period] = p ) | F80: Pool balance at the last period in context. | H80: #,##0
A81: D06-02 | B81: 6 | C81: Pool cash flow | D81: Interest Collected | E81: SUM ( FactPool[interest_collected] ) | F81: Interest collections. | H81: #,##0
A82: D06-03 | B82: 6 | C82: Pool cash flow | D82: Servicing Fees | E82: SUM ( FactPool[servicing_fees] ) | F82: Senior servicing fee (0.5% p.a., assumption). | H82: #,##0
A83: D06-04 | B83: 6 | C83: Pool cash flow | D83: Net Loss (Projected) | E83: SUM ( FactPool[net_loss] ) | F83: Projected net loss under the scenario. | H83: #,##0
A84: D06-05 | B84: 6 | C84: Pool cash flow | D84: Excess Spread | E84: SUM ( FactPool[excess_spread] ) | F84: Interest left after fees and note coupons. | H84: #,##0
A85: D06-06 | B85: 6 | C85: Pool cash flow | D85: Excess Spread % (annualised) | E85: DIVIDE ( SUM ( FactPool[excess_spread] ), SUM ( FactPool[beginning_pool] ) ) * 12 | F85: Annualised excess spread / pool balance. | H85: 0.00%
A86: D06-07 | B86: 6 | C86: Pool cash flow | D86: Cumulative Loss % (Projected) | E86: VAR p = MAX ( FactPool[period] ) RETURN CALCULATE ( MAX ( FactPool[cumulative_loss_pct] ), FactPool[period] = p ) | F86: Cumulative projected net loss / opening pool at the period in context. | H86: 0.00%
A87: D06-08 | B87: 6 | C87: Pool cash flow | D87: OC Ratio | E87: VAR p = MAX ( FactPool[period] ) RETURN CALCULATE ( MAX ( FactPool[oc_ratio] ), FactPool[period] = p ) | F87: Pool balance / (Class A+B+C notes). | H87: 0.000
A88: D06-09 | B88: 6 | C88: Tranche | D88: Tranche Beginning Balance | E88: VAR p = MIN ( FactWaterfall[period] ) RETURN CALCULATE ( SUM ( FactWaterfall[beginning_balance] ), FactWaterfall[period] = p ) | F88: Opening note balance for the first period in context. | H88: #,##0
A89: D06-10 | B89: 6 | C89: Tranche | D89: Tranche Ending Balance | E89: VAR p = MAX ( FactWaterfall[period] ) RETURN CALCULATE ( SUM ( FactWaterfall[ending_balance] ), FactWaterfall[period] = p ) | F89: Closing note balance at the last period in context. | H89: #,##0
... A91: D06-12 | B91: 6 | C91: Tranche | D91: Interest Paid | E91: SUM ( FactWaterfall[interest_paid] ) | F91: Coupon paid out of available interest. | H91: #,##0
A92: D06-13 | B92: 6 | C92: Tranche | D92: Interest Shortfall | E92: [Interest Due] - [Interest Paid] | F92: Unpaid coupon. | G92: Interest Due, Interest Paid | H92: #,##0
A93: D06-14 | B93: 6 | C93: Tranche | D93: Principal Paid | E93: SUM ( FactWaterfall[principal_paid] ) | F93: Principal distributed (sequential A > B > C > Equity). | H93: #,##0
A94: D06-15 | B94: 6 | C94: Tranche | D94: Tranche Writedown | E94: SUM ( FactWaterfall[writedown] ) | F94: Losses allocated to the tranche (Equity first, Class A last). | H94: #,##0
A95: D06-16 | B95: 6 | C95: Tranche | D95: Writedown % of Tranche | E95: DIVIDE ( [Tranche Writedown], CALCULATE ( SUM ( FactWaterfall[beginning_balance] ), FactWaterfall[period] = 1 ) ) | F95: Share of original tranche balance written down. | G95: Tranche Writedown | H95: 0.0%
A96: D06-17 | B96: 6 | C96: Tranche | D96: Credit Enhancement % | E96: MAX ( DimTranche[attachment] ) | F96: Subordination below the tranche (attachment point). | H96: 0.0%
A97: D06-18 | B97: 6 | C97: Tranche | D97: Tranche Loss % (Attach-Detach) | E97: VAR CumLoss = [Cumulative Loss % (Projected)] VAR Attach = MAX ( DimTranche[attachment] ) VAR Detach = MAX ( DimTranche[detachment] ) RETURN DIVIDE ( MAX ( 0, MIN ( CumLoss, Detach ) - Attach ), Detach - Attach ) | F97: Closed-form tranche loss from pool loss and attachment/detachment points; cross-checks the cash-flow write-down. | G97: Cumulative Loss % (Projected) | H97: 0.0%
A98: D06-19 | B98: 6 | C98: Tranche | D98: Principal Available | E98: SUM ( FactPool[scheduled_principal] ) + SUM ( FactPool[prepayments] ) + SUM ( FactPool[recoveries] ) + SUM ( FactPool[excess_spread_used_for_losses] ) | F98: Cash available for sequential principal pay-down. | H98: #,##0
A99: D06-20 | B99: 6 | C99: Tranche | D99: Principal to Class A | E99: VAR BalA = CALCULATE ( SUM ( FactWaterfall[beginning_balance] ), DimTranche[tranche] = "Class A (Senior)" ) RETURN MIN ( [Principal Available], BalA ) | F99: Sequential allocation: senior class receives principal first. | G99: Principal Available | H99: #,##0
A100: D06-21 | B100: 6 | C100: Tranche | D100: Principal to Class B | E100: VAR BalB = CALCULATE ( SUM ( FactWaterfall[beginning_balance] ), DimTranche[tranche] = "Class B (Mezzanine)" ) RETURN MIN ( MAX ( [Principal Available] - [Principal to Class A], 0 ), BalB ) | F100: Mezzanine receives what remains after Class A. | G100: Principal Available, Principal to Class A | H100: #,##0
A101: D06-22 | B101: 6 | C101: Tranche | D101: Tranche Status | E101: SWITCH ( TRUE (), [Writedown % of Tranche] = 0, "Intact", [Writedown % of Tranche] < 0.5, "Impaired", "Wiped out" ) | F101: Intact / impaired / wiped out label. | G101: Writedown % of Tranche
A102: D06-23 | B102: 6 | C102: Triggers | D102: Delinq Trigger Value | E102: SELECTEDVALUE ( ParamDelinqTrigger[Value], 0.12 ) | F102: What-if driven delinq trigger level (default is an ASSUMPTION). | H102: 0.0%
A103: D06-24 | B103: 6 | C103: Triggers | D103: CNL Trigger Value | E103: SELECTEDVALUE ( ParamCNLTrigger[Value], 0.02 ) | F103: What-if driven cnl trigger level (default is an ASSUMPTION). | H103: 0.0%
A104: D06-25 | B104: 6 | C104: Triggers | D104: OC Trigger Value | E104: SELECTEDVALUE ( ParamOCTrigger[Value], 1.05 ) | F104: What-if driven oc trigger level (default is an ASSUMPTION). | H104: 0.00
A105: D06-26 | B105: 6 | C105: Triggers | D105: Delinquency Trigger Status | E105: IF ( [Delinquent 60+ %] > [Delinq Trigger Value], "BREACH", "OK" ) | F105: Tape 60+ DPD % vs delinquency trigger. | G105: Delinq Trigger Value, Delinquent 60+ %
...

Sheet Summary
A1: Day | B1: Focus | C1: Measures
A2: 3 | B2: Core pool, delinquency and weighted-average measures | C2: =COUNTIF('Measure Dictionary'!B:B,3) -> 40
A3: 4 | B3: Time intelligence and trend alerts | C3: =COUNTIF('Measure Dictionary'!B:B,4) -> 24
A4: 5 | B4: Advanced DAX, virtual tables, concentration | C4: =COUNTIF('Measure Dictionary'!B:B,5) -> 14
A5: 6 | B5: Waterfall, tranche allocation and trigger testing | C5: =COUNTIF('Measure Dictionary'!B:B,6) -> 31
A6: 7 | B6: DPD distribution, roll rates and ageing | C6: =COUNTIF('Measure Dictionary'!B:B,7) -> 24
A7: 8 | B7: Vintage / static pool analysis | C7: =COUNTIF('Measure Dictionary'!B:B,8) -> 14
A8: 9 | B8: IFRS 9 ECL framework | C8: =COUNTIF('Measure Dictionary'!B:B,9) -> 26
A9: 10 | B9: Stress testing and what-if | C9: =COUNTIF('Measure Dictionary'!B:B,10) -> 33
A10: 11 | B10: Investor reporting and data tape | C10: =COUNTIF('Measure Dictionary'!B:B,11) -> 10
A11: 12 | B11: Security, governance and validation | C11: =COUNTIF('Measure Dictionary'!B:B,12) -> 6
B12: Total | C12: =SUM(C2:C11) -> 222
B13: Brief requirement | C13: 80
B14: Meets 80+ requirement? | C14: =IF(C12>=C13,"YES","NO") -> YES

Sheet Parameters
A1: Parameter table | B1: DAX | C1: Purpose
A2: ParamDefaultMult | B2: GENERATESERIES ( 0.5, 5, 0.1 ) | C2: Default-rate multiplier (x)
A3: ParamRecoveryHaircut | B3: GENERATESERIES ( 0, 0.5, 0.05 ) | C3: Recovery haircut = additive LGD (pts)
A4: ParamCPRChange | B4: GENERATESERIES ( -0.1, 0.1, 0.01 ) | C4: Change in annual CPR (pts)
A5: ParamRateShock | B5: GENERATESERIES ( 0, 500, 25 ) | C5: Interest-rate shock (bps)
A6: ParamStage2DPD | B6: GENERATESERIES ( 0, 120, 5 ) | C6: Stage 2 DPD threshold (tape = 30, brief = 60)
A7: ParamStage3DPD | B7: GENERATESERIES ( 60, 180, 5 ) | C7: Stage 3 DPD threshold (tape = 90, brief = 120)
A8: ParamDelinqTrigger | B8: GENERATESERIES ( 0.05, 0.25, 0.005 ) | C8: Delinquency trigger level
A9: ParamCNLTrigger | B9: GENERATESERIES ( 0.005, 0.1, 0.0025 ) | C9: Cumulative net loss trigger level
A10: ParamOCTrigger | B10: GENERATESERIES ( 1, 1.3, 0.01 ) | C10: OC ratio trigger (minimum)
